{
  "name": {
    "ar": "موسيقى مجانية على Google Drive ™",
    "am,bn,en,en_AU,en_GB,en_US,es_419,gu,kn,ml,mr,pt_BR,pt_PT,sw,ta,te": "Free Music on Google Drive™",
    "bg": "Безплатна музика в Google Drive ™",
    "ca": "Música gratuïta a Google Drive ™",
    "cs": "Hudba zdarma na Disku Google ™",
    "da,sv": "Gratis musik på Google Drive ™",
    "de": "Kostenlose Musik auf Google Drive ™",
    "el": "Δωρεάν μουσική στο Google Drive ™",
    "es": "Música gratis en Google Drive ™",
    "et": "Tasuta muusika teenuses Google Drive ™",
    "fa": "موسیقی رایگان در Google Drive",
    "fi": "Ilmainen musiikki Google Drive ™ -palvelussa",
    "fil": "Libreng Musika sa Google Drive ™",
    "fr": "Musique gratuite sur Google Drive ™",
    "he": "מוזיקה בחינם ב- Google Drive ™",
    "hi": "Google Drive ™ पर मुफ्त संगीत",
    "hr": "Besplatna glazba na Google disku ™",
    "hu": "Ingyenes zene a Google Drive ™ -on",
    "id": "Musik Gratis di Google Drive ™",
    "it": "Musica gratis su Google Drive ™",
    "ja": "Google Drive™の無料音楽",
    "ko": "Google 드라이브 ™ 무료 음악",
    "lt": "Nemokama muzika „Google“ diske ™",
    "lv": "Bezmaksas mūzika pakalpojumā Google Drive ™",
    "ms": "Muzik Percuma di Google Drive ™",
    "nl": "Gratis muziek op Google Drive ™",
    "no": "Gratis musikk på Google Drive ™",
    "pl": "Darmowa muzyka na Google Drive ™",
    "ro": "Muzică gratuită pe Google Drive ™",
    "ru": "Бесплатная музыка на Google Drive ™",
    "sk": "Bezplatná hudba na Disku Google ™",
    "sl": "Brezplačna glasba v Googlu Drive ™",
    "sr": "Бесплатна музика на Гоогле диску ™",
    "th": "เพลงฟรีบน Google Drive ™",
    "tr": "Google Drive ™ &#39;da Ücretsiz Müzik",
    "uk": "Безкоштовна музика на Google Drive ™",
    "vi": "Âm nhạc miễn phí trên Google Drive ™",
    "zh_CN": "Google Drive™上的免费音乐",
    "zh_TW": "Google Drive™上的免費音樂"
  },
  "short": {
    "ar": "قم بتشغيل الموسيقى الخاصة بك بسرعة من Google Drive أو الكمبيوتر المحلي.",
    "am,bn,en,en_AU,en_GB,en_US,es_419,gu,kn,ml,mr,pt_BR,pt_PT,sw,ta,te": "Play your music quickly from Google Drive or local computer.",
    "bg": "Пускайте музиката си бързо от Google Диск или локален компютър.",
    "ca": "Reprodueix la teva música ràpidament des de Google Drive o l’ordinador local.",
    "cs": "Přehrávejte svou hudbu rychle z Disku Google nebo z místního počítače.",
    "da": "Afspil din musik hurtigt fra Google Drev eller din lokale computer.",
    "de": "Spielen Sie Ihre Musik schnell über Google Drive oder einen lokalen Computer ab.",
    "el": "Αναπαράγετε γρήγορα τη μουσική σας από το Google Drive ή τον τοπικό υπολογιστή.",
    "es": "Reproduce tu música rápidamente desde Google Drive o desde una computadora local.",
    "et": "Esitage oma muusikat kiiresti Google Drive'ist või kohalikust arvutist.",
    "fa": "موسیقی خود را به سرعت از Google Drive یا رایانه محلی پخش کنید.",
    "fi": "Toista musiikkisi nopeasti Google Drivesta tai paikallisesta tietokoneesta.",
    "fil": "I-play nang mabilis ang iyong musika mula sa Google Drive o lokal na computer.",
    "fr": "Jouez votre musique rapidement depuis Google Drive ou un ordinateur local.",
    "he": "הפעל את המוסיקה שלך במהירות מ- Google Drive או מהמחשב המקומי.",
    "hi": "Google ड्राइव या स्थानीय कंप्यूटर से अपना संगीत जल्दी से चलाएं।",
    "hr": "Brzo reproducirajte svoju glazbu s Google diska ili lokalnog računala.",
    "hu": "Gyorsan játssza le a zenét a Google Drive vagy a helyi számítógépen.",
    "id": "Putar musik Anda dengan cepat dari Google Drive atau komputer lokal.",
    "it": "Ascolta la tua musica velocemente da Google Drive o dal computer locale.",
    "ja": "Googleドライブまたはローカルコンピュータから音楽をすばやく再生します。",
    "ko": "Google 드라이브 또는 로컬 컴퓨터에서 음악을 빠르게 재생할 수 있습니다.",
    "lt": "Greitai atkurkite muziką iš „Google“ disko arba vietinio kompiuterio.",
    "lv": "Atskaņojiet mūziku ātri no Google diska vai vietējā datora.",
    "ms": "Mainkan muzik anda dengan cepat dari Google Drive atau komputer tempatan.",
    "nl": "Speel je muziek snel af van Google Drive of een lokale computer.",
    "no": "Spill musikken din raskt fra Google Disk eller lokal datamaskin.",
    "pl": "Szybko odtwarzaj muzykę z Dysku Google lub komputera lokalnego.",
    "ro": "Redați repede muzica dvs. de pe Google Drive sau pe computerul local.",
    "ru": "Слушайте музыку быстро с Google Диска или локального компьютера.",
    "sk": "Prehrávajte svoju hudbu rýchlo zo služby Disk Google alebo z miestneho počítača.",
    "sl": "Predvajajte glasbo hitro iz storitve Google Drive ali lokalnega računalnika.",
    "sr": "Брзо репродукујте музику са Гоогле диска или локалног рачунара.",
    "sv": "Spela din musik snabbt från Google Drive eller den lokala datorn.",
    "th": "เล่นเพลงของคุณอย่างรวดเร็วจาก Google Drive หรือคอมพิวเตอร์ในพื้นที่",
    "tr": "Müziğinizi Google Drive veya yerel bilgisayardan hızlı bir şekilde çalın.",
    "uk": "Швидко відтворюйте музику з Диска Google або локального комп'ютера.",
    "vi": "Phát nhạc nhanh chóng từ Google Drive hoặc máy tính cục bộ.",
    "zh_CN": "从Google云端硬盘或本地计算机快速播放音乐。",
    "zh_TW": "從Google雲端硬盤或本地計算機快速播放音樂。"
  },
  "long": {
    "ar": "قم بتشغيل الموسيقى الخاصة بك مجانًا بسرعة من Google Drive ™. استمع إلى الموسيقى مجانًا دون أي إعلانات مزعجة تقاطع أغانيك.\n\nFree Music on Google Drive ™ هو برنامج مجاني عبر الإنترنت يسمح لك بالاستماع إلى الموسيقى عبر الإنترنت من Google Drive. يتم تخزين ملفات الموسيقى على Google Drive الخاص بك\n\nلست بحاجة إلى تنزيل الموسيقى على جهاز الكمبيوتر الخاص بك قبل أن تتمكن من الاستماع إلى الموسيقى. يمكنك استخدام مشغل الموسيقى عبر الإنترنت لاستيراد الموسيقى مباشرة من Google Drive والاستماع إلى الموسيقى على الفور. الأمر بسيط ، نحن ندعم العديد من التنسيقات (aac ، mp3 ، m4a ، wav ، ogg ، weba ، wma). لا يلزم التثبيت ، لا توجد تكلفة.\n\nوفر وقتك من تنزيل الموسيقى على جهاز الكمبيوتر الخاص بك حيث سيساعدك برنامجنا على الاستماع إلى أغانيك المفضلة من Google Drive.\n\nخطوات استخدام الموسيقى المجانية على Google Drive ™\n1) قم بتثبيت Free Music على Google Drive ™\n2) قم بتحميل الأغاني المفضلة لديك إلى Google Drive ™ (تحميل لمرة واحدة)\n3) ابدأ تشغيل أغانيك من Google Drive ™. يمكنك الوصول إلى أغانيك بغض النظر عن مكان وجودك إذا كنت متصلاً بالإنترنت\n\nهذا أفضل من Spotify لأنه يمكنك إنشاء قوائم التشغيل المخصصة الخاصة بك ولا توجد إعلانات لتعطيل تجربة الاستماع. الحد الوحيد هو خيالك!\n\nإخلاء المسؤولية: يرجى ملاحظة أن هذا الامتداد لا يتم بواسطة Google وإنما بواسطة فريق تطوير مستقل. جميع الحقوق تنتمي لأصحابها. لا تؤيد Google أو ترعى امتداد Chrome هذا. الموسيقى المجانية على Google Drive ™ ليست مملوكة لشركة Google Inc. وليست مرخصة وليست شركة تابعة لها.",
    "am,bn,en,en_AU,en_GB,en_US,es_419,gu,kn,ml,mr,pt_BR,pt_PT,sw,ta,te": "Play your music for free quickly from Google Drive™. Listen to music for free without any annoying ads interrupting your songs.\n\nFree Music on Google Drive™ is a free online software which allows you to listen to music online from your Google Drive. The music files are stored on your Google Drive\n\nYou don't need to download music to your computer before you can listen to music. You can use the online music player to import music directly from your Google Drive and listen to music right away. It's simple, we support many formats (aac, mp3, m4a, wav, ogg, weba, wma). No installation required is required, there is no cost.\n\nSave your time from downloading music to your computer as our software will help you listen to your favorite songs from Google Drive.\n\nSteps to Use Free Music on Google Drive™\n1) Install Free Music on Google Drive™\n2) Upload your favorite songs to your Google Drive™ (One time Upload)\n3) Begin playing your songs from Google Drive™ . Have access to your songs no matter where you are if you are online\n\nThis is better then Spotify because you can make your own custom playlists and there are no ads to disrupt the listening experience. The only limit is your imagination!\n\nDisclaimer: Please note this extension is NOT made by Google and is made by an independent development team. All copyrights belong to their respective owners. Google doesn’t endorse or sponsor this Chrome extension. Free Music on Google Drive™ is not owned by, is not licensed by and is not a subsidiary of Google Inc.",
    "bg": "Пускайте музиката си безплатно бързо от Google Drive ™. Слушайте музика безплатно, без никакви досадни реклами, които да прекъсват песните ви.\n\nБезплатна музика в Google Drive ™ е безплатен онлайн софтуер, който ви позволява да слушате музика онлайн от вашия Google Drive. Музикалните файлове се съхраняват на вашия Google Drive\n\nНе е необходимо да изтегляте музика на компютъра си, преди да можете да слушате музика. Можете да използвате онлайн музикалния плейър, за да импортирате музика директно от Google Drive и да слушате музика веднага. Това е просто, ние поддържаме много формати (aac, mp3, m4a, wav, ogg, weba, wma). Не се изисква инсталиране, няма разходи.\n\nСпестете времето си от изтегляне на музика на вашия компютър, тъй като нашият софтуер ще ви помогне да слушате любимите си песни от Google Drive.\n\nСтъпки за използване на безплатна музика в Google Drive ™\n1) Инсталирайте безплатна музика на Google Drive ™\n2) Качете любимите си песни на вашия Google Drive ™ (еднократно качване)\n3) Започнете да възпроизвеждате песните си от Google Drive ™. Имайте достъп до песните си, независимо къде се намирате, ако сте онлайн\n\nТова е по-добре от Spotify, защото можете да създадете свои собствени плейлисти и няма реклами, които да нарушат слушането. Единственото ограничение е вашето въображение!\n\nОтказ от отговорност: Моля, обърнете внимание, че това разширение НЕ е направено от Google и е направено от независим екип за разработка. Всички авторски права принадлежат на съответните им собственици. Google не одобрява и не спонсорира това разширение за Chrome. Безплатната музика в Google Drive ™ не е собственост, не е лицензирана и не е дъщерно дружество на Google Inc.",
    "ca": "Reprodueix la teva música de forma ràpida des de Google Drive ™. Escolta música de forma gratuïta sense anuncis molestos que interrompin les teves cançons.\n\nFree Music a Google Drive ™ és un programari gratuït en línia que us permet escoltar música en línia des del vostre Google Drive. Els fitxers de música s’emmagatzemen a Google Drive\n\nNo cal que baixeu música a l'ordinador abans de poder escoltar-la. Podeu utilitzar el reproductor de música en línia per importar música directament del vostre Google Drive i escoltar música de seguida. És senzill, admetem molts formats (aac, mp3, m4a, wav, ogg, weba, wma). No cal instal·lar-se, no hi ha cost.\n\nEstalvieu el temps de descarregar música a l’ordinador, ja que el nostre programari us ajudarà a escoltar les vostres cançons preferides de Google Drive.\n\nPassos per utilitzar música gratuïta a Google Drive ™\n1) Instal·leu música gratuïta a Google Drive ™\n2) Pengeu les vostres cançons preferides a Google Drive ™ (càrrega única)\n3) Comenceu a reproduir les vostres cançons des de Google Drive ™. Accediu a les vostres cançons independentment d’on sigueu, si sou en línia\n\nAixò és millor que Spotify, ja que podeu crear les vostres pròpies llistes de reproducció personalitzades i no hi ha anuncis que afectin l’experiència d’escolta. L’únic límit és la vostra imaginació!\n\nExempció de responsabilitat: tingueu en compte que aquesta extensió NO la fa Google i la fa un equip de desenvolupament independent. Tots els drets d'autor pertanyen als seus respectius propietaris. Google no recolza ni patrocina aquesta extensió de Chrome. Música gratuïta a Google Drive ™ no és propietat de, no té llicència ni és filial de Google Inc.",
    "cs": "Přehrávejte si zdarma hudbu rychle z Google Drive ™. Poslouchejte hudbu zdarma, aniž by vaše skladby rušily rušivé reklamy.\n\nFree Music on Google Drive ™ je bezplatný online software, který vám umožní poslouchat hudbu online z vašeho Disku Google. Hudební soubory jsou uloženy na vašem Disku Google\n\nPřed poslechem hudby nemusíte stahovat hudbu do počítače. Online hudební přehrávač můžete použít k importu hudby přímo z Disku Google a poslechu hudby hned. Je to jednoduché, podporujeme mnoho formátů (aac, mp3, m4a, wav, ogg, weba, wma). Není nutná žádná instalace, nejsou zde žádné náklady.\n\nUšetřete čas stahováním hudby do počítače, protože náš software vám pomůže poslouchat vaše oblíbené skladby z Disku Google.\n\nKroky k použití bezplatné hudby na Google Drive ™\n1) Nainstalujte si na Google Drive ™ hudbu zdarma\n2) Nahrajte své oblíbené skladby na svůj Disk Google ™ (jednorázové nahrání)\n3) Začněte přehrávat skladby ze služby Google Drive ™. Máte přístup ke svým skladbám bez ohledu na to, kde jste, pokud jste online\n\nTo je lepší než Spotify, protože si můžete vytvořit vlastní seznamy skladeb a neexistují žádné reklamy, které by rušily zážitek z poslechu. Jediným limitem je vaše představivost!\n\nZřeknutí se odpovědnosti: Upozorňujeme, že toto rozšíření NENÍ vytvořeno společností Google a je vytvořeno nezávislým vývojovým týmem. Všechna autorská práva patří jejich příslušným vlastníkům. Google toto rozšíření pro Chrome nepodporuje ani nesponzoruje. Hudba zdarma na Google Drive ™ není vlastněna, nemá licenci a není dceřinou společností společnosti Google Inc.",
    "da": "Afspil din musik gratis hurtigt fra Google Drive ™. Lyt til musik gratis uden irriterende annoncer, der afbryder dine sange.\n\nGratis musik på Google Drive ™ er en gratis online software, der giver dig mulighed for at lytte til musik online fra dit Google Drive. Musikfilerne er gemt på dit Google Drev\n\nDu behøver ikke at downloade musik til din computer, før du kan lytte til musik. Du kan bruge online musikafspilleren til at importere musik direkte fra dit Google Drev og lytte til musik med det samme. Det er simpelt, vi understøtter mange formater (aac, mp3, m4a, wav, ogg, weba, wma). Der kræves ingen installation, der er ingen omkostninger.\n\nSpar tid på at downloade musik til din computer, da vores software hjælper dig med at lytte til dine yndlingssange fra Google Drive.\n\nTrin til brug af gratis musik på Google Drive ™\n1) Installer gratis musik på Google Drive ™\n2) Upload dine yndlingssange til din Google Drive ™ (Upload én gang)\n3) Begynd at afspille dine sange fra Google Drive ™. Få adgang til dine sange, uanset hvor du er, hvis du er online\n\nDette er bedre end Spotify, fordi du kan oprette dine egne brugerdefinerede afspilningslister, og der er ingen annoncer, der kan forstyrre lytteoplevelsen. Den eneste grænse er din fantasi!\n\nAnsvarsfraskrivelse: Bemærk, at denne udvidelse IKKE er lavet af Google og er lavet af et uafhængigt udviklingsteam. Alle ophavsrettigheder tilhører deres respektive ejere. Google godkender eller sponsorerer ikke denne Chrome-udvidelse. Gratis musik på Google Drive ™ ejes ikke af, er ikke licenseret af og er ikke et datterselskab af Google Inc.",
    "de": "Spielen Sie Ihre Musik schnell und kostenlos über Google Drive ™ ab. Hören Sie kostenlos Musik, ohne dass störende Werbung Ihre Songs unterbricht.\n\nKostenlose Musik auf Google Drive ™ ist eine kostenlose Online-Software, mit der Sie Musik online von Ihrem Google Drive aus hören können. Die Musikdateien werden auf Ihrem Google Drive gespeichert\n\nSie müssen keine Musik auf Ihren Computer herunterladen, bevor Sie Musik hören können. Mit dem Online-Musikplayer können Sie Musik direkt von Ihrem Google Drive importieren und sofort Musik hören. Es ist einfach, wir unterstützen viele Formate (aac, mp3, m4a, wav, ogg, weba, wma). Es ist keine Installation erforderlich, es fallen keine Kosten an.\n\nSparen Sie Zeit beim Herunterladen von Musik auf Ihren Computer, da Sie mit unserer Software Ihre Lieblingslieder von Google Drive anhören können.\n\nSchritte zur Verwendung von kostenloser Musik in Google Drive ™\n1) Installieren Sie kostenlose Musik auf Google Drive ™\n2) Laden Sie Ihre Lieblingssongs auf Ihr Google Drive ™ hoch (einmaliges Hochladen)\n3) Beginnen Sie mit der Wiedergabe Ihrer Songs über Google Drive ™. Haben Sie Zugriff auf Ihre Songs, egal wo Sie sind, wenn Sie online sind\n\nDies ist besser als Spotify, da Sie Ihre eigenen benutzerdefinierten Wiedergabelisten erstellen können und keine Anzeigen vorhanden sind, die das Hörerlebnis stören könnten. Die einzige Grenze ist Ihre Vorstellungskraft!\n\nHaftungsausschluss: Bitte beachten Sie, dass diese Erweiterung NICHT von Google und von einem unabhängigen Entwicklungsteam erstellt wurde. Alle Urheberrechte liegen bei ihren jeweiligen Eigentümern. Google unterstützt oder sponsert diese Chrome-Erweiterung nicht. Kostenlose Musik auf Google Drive ™ gehört nicht, ist nicht lizenziert von und ist keine Tochtergesellschaft von Google Inc.",
    "el": "Παίξτε δωρεάν τη μουσική σας γρήγορα από το Google Drive ™. Ακούστε μουσική δωρεάν χωρίς ενοχλητικές διαφημίσεις που διακόπτουν τα τραγούδια σας.\n\nΗ δωρεάν μουσική στο Google Drive ™ είναι ένα δωρεάν διαδικτυακό λογισμικό που σας επιτρέπει να ακούτε μουσική στο διαδίκτυο από το Google Drive. Τα αρχεία μουσικής αποθηκεύονται στο Google Drive σας\n\nΔεν χρειάζεται να κατεβάσετε μουσική στον υπολογιστή σας για να ακούσετε μουσική. Μπορείτε να χρησιμοποιήσετε το πρόγραμμα αναπαραγωγής μουσικής στο διαδίκτυο για να εισαγάγετε μουσική απευθείας από το Google Drive και να ακούσετε μουσική αμέσως. Είναι απλό, υποστηρίζουμε πολλές μορφές (aac, mp3, m4a, wav, ogg, weba, wma). Δεν απαιτείται εγκατάσταση, δεν υπάρχει κόστος.\n\nΕξοικονομήστε χρόνο από τη λήψη μουσικής στον υπολογιστή σας, καθώς το λογισμικό μας θα σας βοηθήσει να ακούσετε τα αγαπημένα σας τραγούδια από το Google Drive.\n\nΒήματα για τη χρήση δωρεάν μουσικής στο Google Drive ™\n1) Εγκαταστήστε δωρεάν μουσική στο Google Drive ™\n2) Ανεβάστε τα αγαπημένα σας τραγούδια στο Google Drive ™ (Μία φορά μεταφόρτωση)\n3) Ξεκινήστε να παίζετε τα τραγούδια σας από το Google Drive ™. Έχετε πρόσβαση στα τραγούδια σας ανεξάρτητα από το πού βρίσκεστε εάν είστε συνδεδεμένοι στο διαδίκτυο\n\nΑυτό είναι καλύτερο από το Spotify επειδή μπορείτε να δημιουργήσετε τις δικές σας προσαρμοσμένες λίστες αναπαραγωγής και δεν υπάρχουν διαφημίσεις που να διαταράσσουν την εμπειρία ακρόασης. Το μόνο όριο είναι η φαντασία σας!\n\nΑποποίηση ευθυνών: Λάβετε υπόψη ότι αυτή η επέκταση ΔΕΝ έγινε από την Google και γίνεται από ανεξάρτητη ομάδα ανάπτυξης. Όλα τα πνευματικά δικαιώματα ανήκουν στους αντίστοιχους ιδιοκτήτες τους. Η Google δεν υποστηρίζει ούτε χορηγεί αυτήν την επέκταση Chrome. Η δωρεάν μουσική στο Google Drive ™ δεν ανήκει, δεν διαθέτει άδεια και δεν είναι θυγατρική της Google Inc.",
    "es": "Reproduzca su música gratis rápidamente desde Google Drive ™. Escuche música gratis sin anuncios molestos que interrumpan sus canciones.\n\nFree Music en Google Drive ™ es un software en línea gratuito que le permite escuchar música en línea desde su Google Drive. Los archivos de música se almacenan en su Google Drive\n\nNo es necesario descargar música a su computadora para poder escucharla. Puede utilizar el reproductor de música en línea para importar música directamente desde su Google Drive y escuchar música de inmediato. Es simple, admitimos muchos formatos (aac, mp3, m4a, wav, ogg, weba, wma). No se requiere instalación, no hay costo.\n\nAhorre tiempo al descargar música a su computadora, ya que nuestro software lo ayudará a escuchar sus canciones favoritas de Google Drive.\n\nPasos para usar música gratis en Google Drive ™\n1) Instale Free Music en Google Drive ™\n2) Sube tus canciones favoritas a tu Google Drive ™ (carga única)\n3) Comience a reproducir sus canciones desde Google Drive ™. Tenga acceso a sus canciones sin importar dónde se encuentre si está en línea\n\nEsto es mejor que Spotify porque puede crear sus propias listas de reproducción personalizadas y no hay anuncios que interrumpan la experiencia auditiva. ¡El único límite es tu imaginación!\n\nDescargo de responsabilidad: tenga en cuenta que esta extensión NO está hecha por Google y está hecha por un equipo de desarrollo independiente. Todos los derechos de autor pertenecen a sus respectivos dueños. Google no respalda ni patrocina esta extensión de Chrome. Free Music en Google Drive ™ no es propiedad, no tiene licencia ni es una subsidiaria de Google Inc.",
    "et": "Esitage oma muusikat kiiresti Google Drive'ist ™ tasuta. Kuulake muusikat tasuta, ilma et teie lugusid segaksid tüütud reklaamid.\n\nGoogle Drive ™ -is olev tasuta muusika on tasuta veebitarkvara, mis võimaldab teil oma Google Drive'i kaudu muusikat veebis kuulata. Muusikafailid salvestatakse teie Google Drive'i\n\nEnne muusika kuulamist pole vaja muusikat arvutisse alla laadida. Veebipleieri abil saate muusikat otse Google Drive'ist importida ja muusikat kohe kuulata. See on lihtne, me toetame paljusid formaate (aac, mp3, m4a, wav, ogg, weba, wma). Paigaldamine pole vajalik, kulud pole.\n\nSäästke oma aega muusika arvutisse laadimisel, kuna meie tarkvara aitab teil oma lemmiklaule Google Drive'ist kuulata.\n\nToimingud tasuta muusika kasutamiseks Google Drive ™ -s\n1) Installige tasuta muusika Google Drive'i ™\n2) Laadige oma lemmiklaulud oma Google Drive ™ -i üles (ühekordne üleslaadimine)\n3) Alustage oma lugude esitamist teenusest Google Drive ™. Juurdepääs oma lugudele olenemata teie asukohast, kui olete võrgus\n\nSee on parem kui Spotify, sest saate ise oma esitusloendeid koostada ja kuulamiskogemust häirida ei ole reklaame. Ainus piir on teie kujutlusvõime!\n\nKohustustest loobumine: Pange tähele, et seda laiendust EI teinud Google ja seda teeb sõltumatu arendustiim. Kõik autoriõigused kuuluvad nende omanikele. Google ei toeta ega sponsoreeri seda Chrome'i laiendust. Google Drive ™ -is olev tasuta muusika ei kuulu Google Inc.-ile ega ole litsentseeritud ega ole selle tütarettevõte.",
    "fa": "موسیقی خود را به سرعت از Google Drive به صورت رایگان پخش کنید. بدون اینکه تبلیغات مزاحم باعث قطع شدن آهنگ های شما شود ، به رایگان موسیقی گوش دهید.\n\nFree Music on Google Drive ™ یک نرم افزار آنلاین رایگان است که به شما امکان می دهد از Google Drive خود بصورت آنلاین موسیقی گوش دهید. فایل های موسیقی در Google Drive شما ذخیره می شوند\n\nقبل از گوش دادن به موسیقی ، نیازی به بارگیری موسیقی در رایانه ندارید. می توانید با استفاده از پخش کننده موسیقی آنلاین موسیقی را مستقیماً از Google Drive خود وارد کرده و بلافاصله به موسیقی گوش دهید. این ساده است ، ما از بسیاری از قالب ها (aac ، mp3 ، m4a ، wav ، ogg ، weba ، wma) پشتیبانی می کنیم. بدون نیاز به نصب ، هیچ هزینه ای وجود ندارد.\n\nوقت خود را از بارگیری موسیقی در رایانه خود صرفه جویی کنید زیرا نرم افزار ما به شما کمک می کند آهنگ های مورد علاقه خود را از Google Drive گوش دهید.\n\nمراحل استفاده از موسیقی رایگان در Google Drive\n1) نصب موسیقی رایگان در Google Drive\n2) آهنگ های مورد علاقه خود را در Google Drive خود بارگذاری کنید ™ (بارگذاری یک بار)\n3) پخش آهنگ های خود از Google Drive Begin را شروع کنید. در صورت آنلاین بودن به آهنگهای خود دسترسی داشته باشید\n\nاین از Spotify بهتر است زیرا شما می توانید لیست های پخش دلخواه خود را بسازید و هیچ تبلیغی برای برهم زدن تجربه گوش دادن وجود ندارد. تنها محدودیت تخیل شما است!\n\nسلب مسئولیت: لطفاً توجه داشته باشید که این برنامه افزودنی توسط Google ساخته نشده و توسط یک تیم توسعه مستقل ساخته شده است. کلیه حق چاپ به صاحبان مربوطه تعلق دارند. Google این افزونه Chrome را تأیید یا حمایت نمی کند. موسیقی رایگان در Google Drive by متعلق به آن نیست ، مجوز آن را ندارد و از شرکت های تابعه Google Inc نیست.",
    "fi": "Ilmaiset musiikkityökalut on ilmainen online-sovellus, jonka avulla voit kuunnella musiikkia verkossa Google Drivesta. Sinun ei tarvitse ladata musiikkia tietokoneellesi ennen kuin voit kuunnella musiikkia. Voit käyttää Music Player Online -sovellusta musiikin tuomiseen suoraan Google Driveen ja kuunnella musiikkia heti. Se on yksinkertaista, tuemme monia muotoja (aac, mp3, m4a, wav, ogg, weba, wma). Asennusta ei vaadita, ei kustannuksia. Säästä aikaa musiikin lataamisesta tietokoneellesi, koska sovelluksemme auttaa sinua kuuntelemaan suosikkikappaleitasi Google Drivesta.",
    "fil": "Toista musiikkia nopeasti ilmaiseksi Google Drive ™ -palvelusta. Kuuntele musiikkia ilmaiseksi ilman häiritseviä mainoksia keskeyttämättä kappaleitasi.\n\nIlmainen musiikki Google Drivessa ™ on ilmainen online-ohjelmisto, jonka avulla voit kuunnella musiikkia verkossa Google Drivesta. Musiikkitiedostot tallennetaan Google Driveen\n\nSinun ei tarvitse ladata musiikkia tietokoneellesi ennen kuin voit kuunnella musiikkia. Voit käyttää online-musiikkisoitinta tuoda musiikkia suoraan Google Drivesta ja kuunnella musiikkia heti. Se on yksinkertaista, tuemme monia formaatteja (aac, mp3, m4a, wav, ogg, weba, wma). Asennusta ei vaadita, ei ole kustannuksia.\n\nSäästä aikaa lataamalla musiikkia tietokoneellesi, koska ohjelmistomme auttaa sinua kuuntelemaan suosikkikappaleitasi Google Drivesta.\n\nVaiheet ilmaisen musiikin käyttämiseen Google Drivessa ™\n1) Asenna ilmainen musiikki Google Drive ™ -palveluun\n2) Lähetä suosikkikappaleesi Google Drive ™ -palveluun (kertaluontoinen lataus)\n3) Aloita kappaleiden soittaminen Google Drive ™ -palvelusta. Pääset kappaleihisi riippumatta siitä, missä olet, jos olet verkossa\n\nTämä on parempi kuin Spotify, koska voit luoda omia soittolistojasi, eikä kuuntelukokemusta häiritseviä mainoksia ole. Ainoa raja on mielikuvitus!\n\nVastuuvapauslauseke: Huomaa, että tätä laajennusta EI ole tehnyt Google, ja sen on tehnyt riippumaton kehitystiimi. Kaikki tekijänoikeudet kuuluvat omistajilleen. Google ei tue tai sponsoroi tätä Chrome-laajennusta. Google Drive ™: n ilmainen musiikki ei ole Google Inc: n omistuksessa, lisenssillä eikä tytäryhtiö.",
    "fr": "Écoutez votre musique gratuitement et rapidement depuis Google Drive ™. Écoutez de la musique gratuitement sans aucune publicité ennuyeuse interrompant vos chansons.\n\nFree Music on Google Drive ™ est un logiciel en ligne gratuit qui vous permet d'écouter de la musique en ligne depuis votre Google Drive. Les fichiers musicaux sont stockés sur votre Google Drive\n\nVous n'avez pas besoin de télécharger de la musique sur votre ordinateur avant de pouvoir écouter de la musique. Vous pouvez utiliser le lecteur de musique en ligne pour importer de la musique directement à partir de votre Google Drive et écouter de la musique immédiatement. C'est simple, nous supportons de nombreux formats (aac, mp3, m4a, wav, ogg, weba, wma). Aucune installation requise n'est requise, il n'y a aucun coût.\n\nGagnez du temps en téléchargeant de la musique sur votre ordinateur car notre logiciel vous aidera à écouter vos chansons préférées sur Google Drive.\n\nÉtapes pour utiliser la musique gratuite sur Google Drive ™\n1) Installez Free Music sur Google Drive ™\n2) Téléchargez vos chansons préférées sur votre Google Drive ™ (téléchargement unique)\n3) Commencez à lire vos chansons depuis Google Drive ™. Accédez à vos chansons où que vous soyez si vous êtes en ligne\n\nC'est mieux que Spotify car vous pouvez créer vos propres listes de lecture personnalisées et aucune publicité ne perturbe l'expérience d'écoute. La seule limite est votre imagination!\n\nClause de non-responsabilité: veuillez noter que cette extension n'est PAS faite par Google et est faite par une équipe de développement indépendante. Tous les droits d'auteur appartiennent à leurs propriétaires respectifs. Google n'approuve ni ne sponsorise cette extension Chrome. Free Music on Google Drive ™ n'est pas la propriété de, n'est pas licencié par et n'est pas une filiale de Google Inc.",
    "he": "כלי מוסיקה בחינם הוא אפליקציה מקוונת בחינם המאפשרת לך להאזין למוזיקה באופן מקוון מכונן Google שלך. אינך צריך להוריד מוסיקה למחשב לפני שתוכל להאזין למוזיקה. אתה יכול להשתמש בנגן המוסיקה המקוון כדי לייבא מוזיקה ישירות מכונן Google שלך ולהאזין למוזיקה מייד. זה פשוט, אנו תומכים בפורמטים רבים (aac, mp3, m4a, wav, ogg, weba, wma). אין צורך בהתקנה, אין עלות. חסוך את הזמן שלך מהורדת מוסיקה למחשב שלך שכן היישום שלנו יעזור לך להאזין לשירים המועדפים עליך מכונן Google שלך.",
    "hi": "Google Drive ™ से अपने संगीत को जल्दी से मुफ्त में चलाएं। बिना किसी कष्टप्रद विज्ञापनों के अपने गीतों को बाधित किए बिना मुफ्त में संगीत सुनें।\n\nGoogle Drive ™ पर मुफ्त संगीत एक मुफ्त ऑनलाइन सॉफ्टवेयर है जो आपको अपने Google ड्राइव से ऑनलाइन संगीत सुनने की अनुमति देता है। संगीत फ़ाइलें आपके Google ड्राइव पर संग्रहीत की जाती हैं\n\nसंगीत सुनने से पहले आपको अपने कंप्यूटर पर संगीत डाउनलोड करने की आवश्यकता नहीं है। आप अपने Google ड्राइव से सीधे संगीत आयात करने के लिए ऑनलाइन संगीत प्लेयर का उपयोग कर सकते हैं और तुरंत संगीत सुन सकते हैं। यह सरल है, हम कई स्वरूपों (aac, mp3, m4a, wav, ogg, weba, wma) का समर्थन करते हैं। कोई स्थापना आवश्यक नहीं है, कोई लागत नहीं है।\n\nअपने कंप्यूटर पर संगीत डाउनलोड करने से अपना समय बचाएं क्योंकि हमारा सॉफ़्टवेयर Google ड्राइव से आपके पसंदीदा गाने सुनने में आपकी सहायता करेगा।\n\nGoogle Drive ™ पर मुफ्त संगीत का उपयोग करने के लिए कदम\n1) Google Drive ™ पर मुफ्त संगीत स्थापित करें\n2) अपने पसंदीदा गानों को अपने Google Drive ™ (वन टाइम अपलोड) पर अपलोड करें\n3) Google Drive ™ से अपने गाने बजाना शुरू करें। अगर आप ऑनलाइन हैं, तो अपने गीतों तक पहुंच न रखें\n\nयह बेहतर है तब Spotify क्योंकि आप अपने स्वयं के कस्टम प्लेलिस्ट बना सकते हैं और सुनने के अनुभव को बाधित करने के लिए कोई विज्ञापन नहीं हैं। केवल आपकी कल्पना ही एक सीमा है!\n\nअस्वीकरण: कृपया ध्यान दें कि यह एक्सटेंशन Google द्वारा नहीं बनाया गया है और यह एक स्वतंत्र विकास दल द्वारा बनाया गया है। समस्त कॉपीराइट उनके संबंधित स्वामियों की संपत्ति हैं। Google इस क्रोम एक्सटेंशन का समर्थन या प्रायोजन नहीं करता है। Google Drive ™ पर मुफ्त संगीत का स्वामित्व नहीं है, यह लाइसेंस प्राप्त नहीं है और यह Google इंक की सहायक कंपनी नहीं है।",
    "hr": "Besplatno reproducirajte svoju glazbu brzo s Google Drive ™. Slušajte glazbu besplatno, bez ikakvih dosadnih oglasa koji ometaju vaše pjesme.\n\nBesplatna glazba na Google Driveu ™ besplatan je mrežni softver koji vam omogućuje slušanje glazbe putem interneta s vašeg Google diska. Glazbene datoteke pohranjene su na vašem Google disku\n\nNe morate preuzimati glazbu na računalo da biste mogli slušati glazbu. Mrežni glazbeni uređaj možete koristiti za uvoz glazbe izravno s Google pogona i slušanje glazbe odmah. Jednostavno je, podržavamo mnoge formate (aac, mp3, m4a, wav, ogg, weba, wma). Nije potrebna nikakva instalacija, nema troškova.\n\nUštedite vrijeme od preuzimanja glazbe na računalo, jer će vam naš softver pomoći da slušate omiljene pjesme s Google diska.\n\nKoraci za upotrebu besplatne glazbe na Google Driveu ™\n1) Instalirajte besplatnu glazbu na Google Drive ™\n2) Prenesite svoje omiljene pjesme na svoj Google Drive ™ (jednokratno slanje)\n3) Počnite reproducirati svoje pjesme s Google Drive ™. Imajte pristup svojim pjesmama bez obzira gdje se nalazite ako ste na mreži\n\nTo je bolje od Spotifyja, jer možete napraviti vlastite prilagođene popise pjesama, a nema oglasa koji bi ometali iskustvo slušanja. Jedino ograničenje je vaša mašta!\n\nIzjava o odricanju odgovornosti: imajte na umu da ovo proširenje NIJE Google, a izradio ga je neovisni razvojni tim. Sva autorska prava pripadaju njihovim vlasnicima. Google ne podržava ili ne sponzorira ovo proširenje za Chrome. Besplatna glazba na Google Driveu ™ nije u vlasništvu, nije licencirana i nije podružnica Google Inc.",
    "hu": "Gyorsan játssza le a zenét a Google Drive ™ szolgáltatásból. Ingyenes zenehallgatás anélkül, hogy bosszantó hirdetések szakítanák meg a dalait.\n\nAz ingyenes zene a Google Drive-on ™ egy ingyenes online szoftver, amely lehetővé teszi, hogy online zenét hallgasson a Google Drive-ról. A zenefájlokat a Google Drive tárolja\n\nMielőtt zenét hallgathatna, nem kell letöltenie a zenét a számítógépére. Az online zenelejátszó segítségével zenét importálhat közvetlenül a Google Drive-ról, és azonnal meghallgathatja a zenét. Egyszerű, sok formátumot támogatunk (aac, mp3, m4a, wav, ogg, weba, wma). Nincs szükség telepítésre, nincs költség.\n\nTakarítson meg időt a zene számítógépre történő letöltésétől, mivel szoftverünk segít meghallgatni kedvenc dalait a Google Drive-ról.\n\nAz ingyenes zene használatának lépései a Google Drive ™ -on\n1) Telepítse az ingyenes zenét a Google Drive ™ -ra\n2) Töltse fel kedvenc dalait a Google Drive ™ -ra (egyszeri feltöltés)\n3) Kezdje el lejátszani dalait a Google Drive ™ szolgáltatásból. Hozzáférhet a dalaihoz, függetlenül attól, hogy hol tartózkodik, ha online\n\nEz jobb, mint a Spotify, mert saját egyéni lejátszási listákat készíthet, és nincsenek hirdetések, amelyek megzavarnák a hallgatási élményt. Az egyetlen korlát a fantáziád!\n\nJogi nyilatkozat: Felhívjuk figyelmét, hogy ezt a bővítményt NEM a Google készítette, és egy független fejlesztői csapat készítette. Minden szerzői jog a megfelelő tulajdonosoké. A Google nem támogatja vagy szponzorálja ezt a Chrome-bővítményt. Az ingyenes zene a Google Drive ™ -on nem a Google Inc. tulajdonában van, nem rendelkezik engedéllyel és nem leányvállalata.",
    "id": "Putar musik Anda secara gratis dengan cepat dari Google Drive ™. Dengarkan musik secara gratis tanpa iklan mengganggu yang mengganggu lagu Anda.\n\nMusik Gratis di Google Drive ™ adalah perangkat lunak online gratis yang memungkinkan Anda mendengarkan musik online dari Google Drive Anda. File musik disimpan di Google Drive Anda\n\nAnda tidak perlu mengunduh musik ke komputer Anda sebelum dapat mendengarkan musik. Anda dapat menggunakan pemutar musik online untuk mengimpor musik langsung dari Google Drive Anda dan langsung mendengarkan musik. Sederhana saja, kami mendukung banyak format (aac, mp3, m4a, wav, ogg, weba, wma). Tidak diperlukan instalasi, tidak ada biaya.\n\nHemat waktu Anda dari mengunduh musik ke komputer karena perangkat lunak kami akan membantu Anda mendengarkan lagu favorit dari Google Drive.\n\nLangkah-langkah untuk Menggunakan Musik Gratis di Google Drive ™\n1) Pasang Musik Gratis di Google Drive ™\n2) Unggah lagu favorit Anda ke Google Drive ™ (Unggah Sekali)\n3) Mulailah memainkan lagu-lagu Anda dari Google Drive ™. Dapatkan akses ke lagu Anda di mana pun Anda berada jika Anda sedang online\n\nIni lebih baik daripada Spotify karena Anda dapat membuat daftar putar khusus Anda sendiri dan tidak ada iklan yang mengganggu pengalaman mendengarkan. Satu-satunya batasan adalah imajinasi Anda!\n\nPenafian: Harap dicatat ekstensi ini TIDAK dibuat oleh Google dan dibuat oleh tim pengembangan independen. Semua hak cipta adalah milik masing-masing pemiliknya. Google tidak mendukung atau mensponsori ekstensi Chrome ini. Musik Gratis di Google Drive ™ tidak dimiliki oleh, tidak dilisensikan oleh, dan bukan merupakan anak perusahaan dari Google Inc.",
    "it": "Riproduci la tua musica gratuitamente rapidamente da Google Drive ™. Ascolta la musica gratuitamente senza fastidiose pubblicità che interrompono le tue canzoni.\n\nFree Music on Google Drive ™ è un software online gratuito che ti consente di ascoltare musica online dal tuo Google Drive. I file musicali vengono archiviati sul tuo Google Drive\n\nNon è necessario scaricare musica sul computer prima di poterla ascoltare. Puoi utilizzare il lettore musicale online per importare musica direttamente da Google Drive e ascoltare subito la musica. È semplice, supportiamo molti formati (aac, mp3, m4a, wav, ogg, weba, wma). Non è richiesta alcuna installazione, non ci sono costi.\n\nRisparmia tempo scaricando musica sul tuo computer poiché il nostro software ti aiuterà ad ascoltare le tue canzoni preferite da Google Drive.\n\nPassaggi per utilizzare musica gratis su Google Drive ™\n1) Installa musica gratis su Google Drive ™\n2) Carica le tue canzoni preferite sul tuo Google Drive ™ (caricamento una tantum)\n3) Inizia a riprodurre i tuoi brani da Google Drive ™. Avere accesso alle tue canzoni indipendentemente da dove ti trovi se sei online\n\nQuesto è meglio di Spotify perché puoi creare le tue playlist personalizzate e non ci sono pubblicità per interrompere l'esperienza di ascolto. L'unico limite è la tua immaginazione!\n\nDichiarazione di non responsabilità: si prega di notare che questa estensione NON è realizzata da Google ed è realizzata da un team di sviluppo indipendente. Tutti i diritti d'autore appartengono ai rispettivi proprietari. Google non approva né sponsorizza questa estensione di Chrome. Free Music on Google Drive ™ non è di proprietà di, non è concesso in licenza da e non è una consociata di Google Inc.",
    "ja": "GoogleDrive™から音楽を無料ですばやく再生します。迷惑な広告が曲を邪魔することなく、無料で音楽を聴きます。\n\nGoogleDrive™の無料音楽は、Googleドライブからオンラインで音楽を聴くことができる無料のオンラインソフトウェアです。音楽ファイルはGoogleドライブに保存されます\n\n音楽を聴く前に、コンピュータに音楽をダウンロードする必要はありません。オンラインミュージックプレーヤーを使用して、Googleドライブから直接音楽をインポートし、すぐに音楽を聴くことができます。シンプルで、多くのフォーマット（aac、mp3、m4a、wav、ogg、weba、wma）をサポートしています。インストールは必要ありません、費用はかかりません。\n\nGoogleのソフトウェアを使用すると、Googleドライブからお気に入りの曲を聴くことができるため、音楽をパソコンにダウンロードする時間を節約できます。\n\nGoogleDrive™で無料の音楽を使用する手順\n1）GoogleDrive™に無料の音楽をインストールする\n2）お気に入りの曲をGoogleDrive™にアップロードします（1回限りのアップロード）\n3）Googleドライブ™から曲の再生を開始します。オンラインであれば、どこにいても曲にアクセスできます\n\n独自のカスタムプレイリストを作成でき、リスニング体験を妨げる広告がないため、これはSpotifyよりも優れています。唯一の制限はあなたの想像力です！\n\n免責事項：この拡張機能はGoogleによって作成されたものではなく、独立した開発チームによって作成されたものであることに注意してください。すべての著作権はそれぞれの所有者に帰属します。 Googleは、このChrome拡張機能を推奨または後援していません。 GoogleDrive™の無料音楽は、Google Inc.が所有、ライセンス供与、および子会社ではありません。",
    "ko": "Google Drive ™에서 무료로 빠르게 음악을 재생합니다. 노래를 방해하는 성가신 광고없이 무료로 음악을 듣습니다.\n\nGoogle Drive ™의 무료 음악은 Google Drive에서 온라인으로 음악을들을 수있는 무료 온라인 소프트웨어입니다. 음악 파일은 Google 드라이브에 저장됩니다.\n\n음악을 듣기 전에 컴퓨터에 음악을 다운로드 할 필요가 없습니다. 온라인 음악 플레이어를 사용하여 Google 드라이브에서 직접 음악을 가져오고 즉시 음악을들을 수 있습니다. 간단합니다. 다양한 형식 (aac, mp3, m4a, wav, ogg, weba, wma)을 지원합니다. 설치가 필요하지 않으며 비용이 들지 않습니다.\n\nGoogle 소프트웨어를 사용하면 Google 드라이브에서 좋아하는 노래를들을 수 있으므로 음악을 컴퓨터로 다운로드하는 시간을 절약 할 수 있습니다.\n\nGoogle Drive ™에서 무료 음악을 사용하는 단계\n1) Google Drive ™에 무료 음악 설치\n2) 좋아하는 노래를 Google Drive ™에 업로드 (1 회 업로드)\n3) Google Drive ™에서 노래 재생을 시작합니다. 온라인 상태라면 어디에 있든 노래에 액세스 할 수 있습니다.\n\n나만의 맞춤 재생 목록을 만들 수 있고 청취 경험을 방해하는 광고가 없기 때문에 Spotify보다 낫습니다. 유일한 한계는 당신의 상상력입니다!\n\n면책 조항 :이 확장은 Google에서 만든 것이 아니며 독립적 인 개발 팀에서 만든 것입니다. 모든 저작권은 해당 소유자에게 있습니다. Google은이 Chrome 확장 프로그램을 보증하거나 후원하지 않습니다. Google Drive ™의 무료 음악은 Google Inc.의 소유가 아니며 라이센스가 부여되지 않으며 Google Inc.의 자회사가 아닙니다.",
    "lt": "Greitai grokite muziką iš „Google“ disko ™. Klausykitės muzikos nemokamai be jokių erzinančių skelbimų, trukdančių jūsų dainoms.\n\nNemokama muzika „Google“ diske ™ yra nemokama internetinė programinė įranga, leidžianti klausytis muzikos internetu iš „Google“ disko. Muzikos failai saugomi jūsų „Google“ diske\n\nKad galėtumėte klausytis muzikos, nereikia atsisiųsti muzikos į kompiuterį. Galite naudoti internetinį muzikos grotuvą, norėdami importuoti muziką tiesiai iš „Google“ disko ir iškart klausytis muzikos. Tai paprasta, mes palaikome daug formatų (aac, mp3, m4a, wav, ogg, weba, wma). Nereikia diegti, nėra jokių išlaidų.\n\nSutaupykite laiko atsisiųsdami muziką į savo kompiuterį, nes mūsų programinė įranga padės klausytis mėgstamų dainų iš „Google“ disko.\n\nNemokamos muzikos naudojimo „Google“ diske ™ veiksmai\n1) Įdiekite nemokamą muziką „Google“ diske\n2) Įkelkite mėgstamas dainas į „Google“ diską (vieną kartą įkelkite)\n3) Pradėkite groti dainas iš „Google“ disko. Turite prieigą prie savo dainų, kad ir kur būtumėte, jei esate prisijungę\n\nTai geriau nei „Spotify“, nes galite susikurti savo pasirinktus grojaraščius ir nėra skelbimų, trukdančių klausytis. Vienintelė riba yra jūsų fantazija!\n\nAtsakomybės apribojimas: atkreipkite dėmesį, kad šį plėtinį NEGALI „Google“, o jį atlieka nepriklausoma kūrėjų komanda. Visos autorių teisės priklauso jų savininkams. „Google“ nepatvirtina ir neremia šio „Chrome“ plėtinio. „Google Drive“ nemokama muzika nepriklauso „Google Inc.“, nėra licencijuota ir nėra „Google Inc.“ dukterinė įmonė.",
    "lv": "Ātri atskaņojiet mūziku no Google diska ™. Klausieties mūziku bez maksas, netraucējot reklāmas, kas pārtrauc jūsu dziesmas.\n\nBezmaksas mūzika pakalpojumā Google disks ™ ir bezmaksas tiešsaistes programmatūra, kas ļauj klausīties mūziku tiešsaistē no sava Google diska. Mūzikas faili tiek glabāti jūsu Google diskā\n\nLai varētu klausīties mūziku, mūzika nav jāielādē datorā. Varat izmantot tiešsaistes mūzikas atskaņotāju, lai importētu mūziku tieši no sava Google diska un uzreiz klausītos mūziku. Tas ir vienkārši, mēs atbalstām daudzus formātus (aac, mp3, m4a, wav, ogg, weba, wma). Instalācija nav nepieciešama, par to nav jāmaksā.\n\nIetaupiet laiku, lejupielādējot mūziku datorā, jo mūsu programmatūra palīdzēs klausīties iecienītākās dziesmas no Google diska.\n\nNorādījumi par bezmaksas mūzikas izmantošanu pakalpojumā Google disks ™\n1) Google diskā ™ instalējiet bezmaksas mūziku\n2) Augšupielādējiet iecienītās dziesmas savā Google diskā ™ (vienreizēja augšupielāde)\n3) Sāciet atskaņot dziesmas no Google diska ™. Piekļūstiet savām dziesmām neatkarīgi no atrašanās vietas, ja esat tiešsaistē\n\nTas ir labāk nekā Spotify, jo jūs varat izveidot savus pielāgotos atskaņošanas sarakstus, un nav nevienas reklāmas, kas traucētu klausīšanās pieredzi. Vienīgais ierobežojums ir jūsu iztēle!\n\nAtruna: lūdzu, ņemiet vērā, ka šo paplašinājumu NAV izveidojis Google, un to veic neatkarīga izstrādātāju komanda. Visas autortiesības pieder to attiecīgajiem īpašniekiem. Google neapstiprina un sponsorē šo Chrome paplašinājumu. Bezmaksas mūzika pakalpojumā Google disks ™ nepieder Google Inc., tā nav licencēta un nav Google Inc. meitasuzņēmums.",
    "ms": "Mainkan muzik anda secara percuma dari Google Drive ™. Dengarkan muzik secara percuma tanpa ada iklan yang mengganggu lagu anda.\n\nMuzik Percuma di Google Drive ™ adalah perisian dalam talian percuma yang membolehkan anda mendengar muzik dalam talian dari Google Drive anda. Fail muzik disimpan di Google Drive anda\n\nAnda tidak perlu memuat turun muzik ke komputer sebelum dapat mendengarkan muzik. Anda boleh menggunakan pemain muzik dalam talian untuk mengimport muzik secara langsung dari Google Drive anda dan segera mendengar muzik. Sangat mudah, kami menyokong banyak format (aac, mp3, m4a, wav, ogg, weba, wma). Tidak diperlukan pemasangan, tidak ada kos.\n\nJimat masa anda dari memuat turun muzik ke komputer anda kerana perisian kami akan membantu anda mendengarkan lagu-lagu kegemaran anda dari Google Drive.\n\nLangkah Menggunakan Muzik Percuma di Google Drive ™\n1) Pasang Muzik Percuma di Google Drive ™\n2) Muat naik lagu kegemaran anda ke Google Drive ™ anda (Muat Naik sekali)\n3) Mulailah memainkan lagu anda dari Google Drive ™. Dapatkan akses ke lagu anda di mana sahaja anda berada jika anda berada dalam talian\n\nIni lebih baik daripada Spotify kerana anda boleh membuat senarai main tersuai dan tidak ada iklan yang mengganggu pengalaman mendengar. Satu-satunya had adalah imaginasi anda!\n\nPenafian: Harap maklum bahawa peluasan ini TIDAK dibuat oleh Google dan dibuat oleh pasukan pembangunan bebas. Semua hak cipta adalah milik pemiliknya masing-masing. Google tidak menyokong atau menaja pelanjutan Chrome ini. Muzik Percuma di Google Drive ™ tidak dimiliki oleh, tidak dilesenkan oleh dan bukan anak syarikat Google Inc.",
    "nl": "Speel uw muziek snel gratis af vanaf Google Drive ™. Luister gratis naar muziek zonder vervelende advertenties die uw liedjes onderbreken.\n\nGratis muziek op Google Drive ™ is gratis online software waarmee u online naar muziek kunt luisteren vanaf uw Google Drive. De muziekbestanden worden opgeslagen op uw Google Drive\n\nU hoeft geen muziek naar uw computer te downloaden voordat u naar muziek kunt luisteren. U kunt de online muziekspeler gebruiken om muziek rechtstreeks uit uw Google Drive te importeren en direct naar muziek te luisteren. Het is eenvoudig, we ondersteunen vele formaten (aac, mp3, m4a, wav, ogg, weba, wma). Er is geen installatie vereist, er zijn geen kosten aan verbonden.\n\nBespaar tijd bij het downloaden van muziek naar uw computer, want onze software helpt u naar uw favoriete nummers te luisteren vanuit Google Drive.\n\nStappen om gratis muziek te gebruiken op Google Drive ™\n1) Installeer gratis muziek op Google Drive ™\n2) Upload uw favoriete nummers naar uw Google Drive ™ (eenmalige upload)\n3) Begin met het afspelen van uw nummers vanuit Google Drive ™. Heb toegang tot uw nummers, ongeacht waar u zich bevindt als u online bent\n\nDit is beter dan Spotify omdat je je eigen aangepaste afspeellijsten kunt maken en er geen advertenties zijn die de luisterervaring verstoren. De enige beperking is uw fantasie!\n\nDisclaimer: Let op: deze extensie is NIET gemaakt door Google en is gemaakt door een onafhankelijk ontwikkelingsteam. Alle auteursrechten behoren toe aan hun respectievelijke eigenaren. Google onderschrijft of sponsort deze Chrome-extensie niet. Gratis muziek op Google Drive ™ is geen eigendom van, heeft geen licentie van en is geen dochteronderneming van Google Inc.",
    "no": "Spill musikken din gratis raskt fra Google Drive ™. Lytt til musikk gratis uten irriterende annonser som forstyrrer sangene dine.\n\nGratis musikk på Google Drive ™ er en gratis online programvare som lar deg lytte til musikk online fra Google Disk. Musikkfilene er lagret på Google Disk\n\nDu trenger ikke å laste ned musikk til datamaskinen din før du kan lytte til musikk. Du kan bruke den elektroniske musikkspilleren til å importere musikk direkte fra Google Drive og lytte til musikk med en gang. Det er enkelt, vi støtter mange formater (aac, mp3, m4a, wav, ogg, weba, wma). Ingen installasjon kreves, det er ingen kostnader.\n\nSpar tid på å laste ned musikk til datamaskinen din, da programvaren vår hjelper deg å lytte til favorittsangene dine fra Google Drive.\n\nFremgangsmåte for å bruke gratis musikk på Google Drive ™\n1) Installer gratis musikk på Google Drive ™\n2) Last opp favorittsangene dine til Google Drive ™ (en gangs opplasting)\n3) Begynn å spille sangene dine fra Google Drive ™. Har tilgang til sangene dine uansett hvor du er hvis du er online\n\nDette er bedre enn Spotify fordi du kan lage dine egne tilpassede spillelister, og det er ingen annonser som kan forstyrre lytteopplevelsen. Den eneste grensen er fantasien din!\n\nAnsvarsfraskrivelse: Vær oppmerksom på at denne utvidelsen IKKE er laget av Google og er laget av et uavhengig utviklingsteam. Alle opphavsrettigheter tilhører deres respektive eiere. Google støtter ikke eller sponser denne Chrome-utvidelsen. Gratis musikk på Google Drive ™ eies ikke av, er ikke lisensiert av og er ikke et datterselskap av Google Inc.",
    "pl": "Odtwarzaj szybko swoją muzykę za darmo z Google Drive ™. Słuchaj muzyki za darmo, bez irytujących reklam, które przerywają Twoje utwory.\n\nFree Music on Google Drive ™ to darmowe oprogramowanie online, które umożliwia słuchanie muzyki online z Dysku Google. Pliki muzyczne są przechowywane na Twoim Dysku Google\n\nNie musisz pobierać muzyki na komputer, aby móc słuchać muzyki. Możesz użyć odtwarzacza muzyki online, aby importować muzykę bezpośrednio z Dysku Google i od razu słuchać muzyki. To proste, obsługujemy wiele formatów (aac, mp3, m4a, wav, ogg, weba, wma). Nie jest wymagana instalacja, nie ma żadnych kosztów.\n\nOszczędź czas na pobieraniu muzyki na komputer, ponieważ nasze oprogramowanie pomoże Ci słuchać ulubionych piosenek z Dysku Google.\n\nKroki, aby korzystać z bezpłatnej muzyki na Google Drive ™\n1) Zainstaluj darmową muzykę na Google Drive ™\n2) Prześlij swoje ulubione utwory na dysk Google Drive ™ (jednorazowe przesyłanie)\n3) Rozpocznij odtwarzanie swoich utworów z Google Drive ™. Miej dostęp do swoich piosenek bez względu na to, gdzie jesteś, jeśli jesteś online\n\nJest to lepsze niż Spotify, ponieważ możesz tworzyć własne niestandardowe listy odtwarzania i nie ma żadnych reklam, które zakłócałyby wrażenia słuchowe. Jedynym ograniczeniem jest Twoja wyobraźnia!\n\nZastrzeżenie: należy pamiętać, że to rozszerzenie NIE zostało stworzone przez Google i zostało stworzone przez niezależny zespół programistów. Wszystkie prawa autorskie należą do ich odpowiednich właścicieli. Google nie popiera ani nie sponsoruje tego rozszerzenia Chrome. Free Music on Google Drive ™ nie jest własnością, nie jest licencjonowana i nie jest spółką zależną Google Inc.",
    "ro": "Redați-vă muzica gratuit rapid de pe Google Drive ™. Ascultați muzică gratuit, fără reclame enervante care să vă întrerupă melodiile.\n\nFree Music on Google Drive ™ este un software online gratuit care vă permite să ascultați muzică online de pe Google Drive. Fișierele muzicale sunt stocate pe Google Drive\n\nNu trebuie să descărcați muzică pe computer înainte de a putea asculta muzică. Puteți utiliza playerul de muzică online pentru a importa muzică direct din Google Drive și pentru a asculta muzică imediat. Este simplu, acceptăm multe formate (aac, mp3, m4a, wav, ogg, weba, wma). Nu este necesară instalarea, nu există costuri.\n\nEconomisiți-vă timpul descărcând muzică pe computer, deoarece software-ul nostru vă va ajuta să ascultați melodiile preferate de pe Google Drive.\n\nPași pentru utilizarea muzicii gratuite pe Google Drive ™\n1) Instalați Muzică gratuită pe Google Drive ™\n2) Încărcați melodiile preferate pe Google Drive ™ (Încărcare o singură dată)\n3) Începeți să redați melodiile din Google Drive ™. Aveți acces la melodiile dvs., indiferent unde vă aflați, dacă sunteți online\n\nAcest lucru este mai bun decât Spotify, deoarece vă puteți crea propriile playlisturi personalizate și nu există reclame care să perturbe experiența de ascultare. Singura limită este imaginația ta!\n\nDeclinare de responsabilitate: Rețineți că această extensie NU este realizată de Google și este realizată de o echipă de dezvoltare independentă. Toate drepturile de autor aparțin proprietarilor respectivi. Google nu aprobă sau sponsorizează această extensie Chrome. Muzica gratuită pe Google Drive ™ nu este deținută, nu este licențiată și nu este o filială a Google Inc.",
    "ru": "Слушайте музыку быстро бесплатно с Google Drive ™. Слушайте музыку бесплатно без раздражающей рекламы, прерывающей ваши песни.\n\nБесплатная музыка на Google Диске ™ - это бесплатное онлайн-программное обеспечение, которое позволяет вам слушать музыку онлайн с вашего Google Диска. Музыкальные файлы хранятся на вашем Google Диске.\n\nВам не нужно загружать музыку на свой компьютер, прежде чем вы сможете слушать музыку. Вы можете использовать музыкальный онлайн-проигрыватель, чтобы импортировать музыку прямо с Google Диска и сразу же слушать музыку. Все просто, мы поддерживаем множество форматов (aac, mp3, m4a, wav, ogg, weba, wma). Никакой установки не требуется, это бесплатно.\n\nСэкономьте время, скачивая музыку на свой компьютер, так как наше программное обеспечение поможет вам слушать ваши любимые песни с Google Диска.\n\nШаги по использованию бесплатной музыки на Google Диске ™\n1) Установите бесплатную музыку на Google Диск ™\n2) Загрузите свои любимые песни на свой Google Диск ™ (однократная загрузка)\n3) Начните играть свои песни с Google Drive ™. Получите доступ к своим песням, где бы вы ни находились, если вы в сети\n\nЭто лучше, чем Spotify, потому что вы можете создавать свои собственные списки воспроизведения, и нет рекламы, которая мешает прослушиванию. Единственным ограничением является ваше воображение!\n\nОтказ от ответственности: обратите внимание, что это расширение НЕ создано Google, а создано независимой командой разработчиков. Все авторские права принадлежат их владельцам. Google не поддерживает и не спонсирует это расширение Chrome. Бесплатная музыка на Google Диске ™ не принадлежит, не лицензируется и не является дочерней компанией Google Inc.",
    "sk": "Prehrávajte si hudbu rýchlo zadarmo z Disku Google ™. Počúvajte hudbu zadarmo bez toho, aby vám vaše skladby rušili nepríjemné reklamy.\n\nFree Music on Google Drive ™ je bezplatný online softvér, ktorý vám umožní počúvať hudbu online z vášho Disku Google. Hudobné súbory sú uložené na vašom Disku Google\n\nPred počúvaním hudby si nemusíte do počítača sťahovať hudbu. Online hudobný prehrávač môžete použiť na importovanie hudby priamo z Disku Google a okamžité počúvanie hudby. Je to jednoduché, podporujeme mnoho formátov (aac, mp3, m4a, wav, ogg, weba, wma). Nie je potrebná žiadna inštalácia, nie sú tu žiadne náklady.\n\nUšetrite čas sťahovaním hudby do počítača, pretože náš softvér vám pomôže počúvať vaše obľúbené skladby z Disku Google.\n\nKroky na použitie bezplatnej hudby na Disku Google ™\n1) Nainštalujte si hudbu zadarmo na Disk Google ™\n2) Nahrajte svoje obľúbené skladby na svoj disk Google Drive ™ (jednorazové nahranie)\n3) Začnite hrať svoje skladby zo služby Google Drive ™. Máte prístup k svojim skladbám bez ohľadu na to, kde ste, či ste online\n\nTo je lepšie ako Spotify, pretože si môžete vytvoriť vlastné zoznamy skladieb a neexistujú žiadne reklamy, ktoré by rušili zážitok z počúvania. Jediným limitom je vaša fantázia!\n\nZrieknutie sa zodpovednosti: Upozorňujeme, že toto rozšírenie NIE je vyrobené spoločnosťou Google a je vyrobené nezávislým vývojovým tímom. Všetky autorské práva patria ich príslušným vlastníkom. Google toto rozšírenie pre Chrome nepodporuje ani nesponzoruje. Hudbu zadarmo na Disku Google ™ nevlastní spoločnosť Google, nemá na ňu licenciu a nie je jej dcérskou spoločnosťou.",
    "sl": "Hitro predvajajte svojo glasbo iz storitve Google Drive ™. Brezplačno poslušajte glasbo, ne da bi vam nadležni oglasi prekinili skladbe.\n\nBrezplačna glasba na Google Drive ™ je brezplačna spletna programska oprema, ki omogoča poslušanje glasbe v spletu z vašega Google Drive. Glasbene datoteke so shranjene v vašem Google Drive\n\nPreden lahko poslušate glasbo, vam ni treba naložiti glasbe v računalnik. S spletnim predvajalnikom glasbe lahko glasbo uvozite neposredno iz Googla Drive in jo takoj poslušate. Preprosto je, podpiramo številne formate (aac, mp3, m4a, wav, ogg, weba, wma). Potrebna ni nobena namestitev, ni stroškov.\n\nPrihranite čas pred prenosom glasbe v računalnik, saj vam bo naša programska oprema pomagala poslušati vaše najljubše pesmi iz storitve Google Drive.\n\nKoraki za uporabo brezplačne glasbe v storitvi Google Drive ™\n1) Namestite brezplačno glasbo na Google Drive ™\n2) Naložite svoje najljubše pesmi v Google Drive ™ (enkratni prenos)\n3) Začnite predvajati svoje pesmi iz storitve Google Drive ™. Imejte dostop do svojih pesmi, ne glede na to, kje ste, če ste v spletu\n\nTo je bolje kot Spotify, ker si lahko ustvarite lastne sezname predvajanja in ni oglasov, ki bi motili izkušnjo poslušanja. Edina omejitev je vaša domišljija!\n\nOmejitev odgovornosti: upoštevajte, da te razširitve NE izdeluje Google in jo je izdelala neodvisna razvojna skupina. Vse avtorske pravice pripadajo njihovim lastnikom. Google ne podpira in ne sponzorira te razširitve za Chrome. Brezplačna glasba na Googlu Drive ™ ni v lasti družbe Google Licence in ni podružnica družbe Google Inc.",
    "sr": "Репродукујте музику бесплатно са Гоогле Дриве ™. Слушајте музику бесплатно, без досадних огласа који ометају ваше песме.\n\nБесплатна музика на Гоогле диску ™ је бесплатан мрежни софтвер који вам омогућава да музику слушате на мрежи са Гоогле диска. Музичке датотеке се чувају на вашем Гоогле диску\n\nНе морате да преузимате музику на рачунар да бисте могли да слушате музику. Помоћу мрежног музичког плејера можете да увезете музику директно са Гоогле диска и одмах је слушате. Једноставно је, подржавамо многе формате (аац, мп3, м4а, вав, огг, веба, вма). Није потребна никаква инсталација, нема трошкова.\n\nУштедите време од преузимања музике на рачунар, јер ће вам наш софтвер помоћи да слушате омиљене песме са Гоогле диска.\n\nКораци за коришћење бесплатне музике на Гоогле Дриве ™\n1) Инсталирајте бесплатну музику на Гоогле Дриве ™\n2) Отпремите своје омиљене песме на свој Гоогле Дриве ™ (једнократно отпремање)\n3) Почните да репродукујете своје песме са Гоогле Дриве ™. Имајте приступ својим песмама без обзира где се налазите ако сте на мрежи\n\nОво је боље од Спотифи-а, јер можете сами да направите сопствене плејлисте и нема огласа који би ометали искуство слушања. Једино ограничење је ваша машта!\n\nИзјава о одрицању одговорности: Имајте на уму да ово проширење НИЈЕ Гоогле, а направио га је независни развојни тим. Сва ауторска права припадају њиховим власницима. Гоогле не подржава и не спонзорише ово Цхроме проширење. Бесплатна музика на Гоогле Дриве ™ -у није у власништву, није лиценцирана и није подружница компаније Гоогле Инц.",
    "sv": "Spela din musik gratis snabbt från Google Drive ™. Lyssna på musik gratis utan att irriterande annonser stör dina låtar.\n\nGratis musik på Google Drive ™ är en gratis programvara online som låter dig lyssna på musik online från din Google Drive. Musikfilerna lagras på din Google Drive\n\nDu behöver inte ladda ner musik till din dator innan du kan lyssna på musik. Du kan använda musikspelaren online för att importera musik direkt från din Google Drive och lyssna på musik direkt. Det är enkelt, vi stöder många format (aac, mp3, m4a, wav, ogg, weba, wma). Ingen installation krävs krävs utan kostnad.\n\nSpara tid på att ladda ner musik till din dator, eftersom vår programvara hjälper dig att lyssna på dina favoritlåtar från Google Drive.\n\nSteg för att använda gratis musik på Google Drive ™\n1) Installera gratis musik på Google Drive ™\n2) Ladda upp dina favoritlåtar till din Google Drive ™ (uppladdning en gång)\n3) Börja spela dina låtar från Google Drive ™. Har tillgång till dina låtar oavsett var du är om du är online\n\nDetta är bättre än Spotify eftersom du kan skapa dina egna spellistor och det finns inga annonser som kan störa lyssnarupplevelsen. Den enda gränsen är din fantasi!\n\nAnsvarsfriskrivning: Observera att denna tillägg INTE är gjord av Google och görs av ett oberoende utvecklingsteam. Alla upphovsrätt tillhör respektive ägare. Google stöder inte eller sponsrar detta Chrome-tillägg. Gratis musik på Google Drive ™ ägs inte av, är inte licensierat av och är inte ett dotterbolag till Google Inc.",
    "th": "เล่นเพลงของคุณได้ฟรีอย่างรวดเร็วจาก Google Drive ™ ฟังเพลงฟรีโดยไม่มีโฆษณาที่น่ารำคาญมารบกวนเพลงของคุณ\n\nเพลงฟรีบน Google Drive ™เป็นซอฟต์แวร์ออนไลน์ฟรีที่ให้คุณฟังเพลงออนไลน์จาก Google ไดรฟ์ของคุณ ไฟล์เพลงจะถูกเก็บไว้ใน Google Drive ของคุณ\n\nคุณไม่จำเป็นต้องดาวน์โหลดเพลงลงในคอมพิวเตอร์ก่อนจึงจะสามารถฟังเพลงได้ คุณสามารถใช้เครื่องเล่นเพลงออนไลน์เพื่อนำเข้าเพลงโดยตรงจาก Google ไดรฟ์ของคุณและฟังเพลงได้ทันที ง่ายมากเรารองรับหลายรูปแบบ (aac, mp3, m4a, wav, ogg, weba, wma) ไม่จำเป็นต้องติดตั้งไม่มีค่าใช้จ่าย\n\nประหยัดเวลาของคุณจากการดาวน์โหลดเพลงลงในคอมพิวเตอร์ของคุณเนื่องจากซอฟต์แวร์ของเราจะช่วยให้คุณฟังเพลงโปรดจาก Google Drive\n\nขั้นตอนในการใช้เพลงฟรีบน Google Drive ™\n1) ติดตั้งเพลงฟรีบน Google Drive ™\n2) อัปโหลดเพลงโปรดของคุณไปยัง Google Drive ™ (อัปโหลดครั้งเดียว)\n3) เริ่มเล่นเพลงของคุณจาก Google Drive ™ เข้าถึงเพลงของคุณได้ไม่ว่าคุณจะอยู่ที่ไหนหากคุณออนไลน์\n\nนี่จะดีกว่า Spotify เพราะคุณสามารถสร้างเพลย์ลิสต์ของคุณเองได้และไม่มีโฆษณาใด ๆ มารบกวนประสบการณ์การฟัง ขีด จำกัด เดียวคือจินตนาการของคุณ!\n\nข้อจำกัดความรับผิดชอบ: โปรดทราบว่าส่วนขยายนี้ไม่ได้สร้างโดย Google และสร้างโดยทีมพัฒนาอิสระ ลิขสิทธิ์ทั้งหมดเป็นของเจ้าของที่เกี่ยวข้อง Google ไม่รับรองหรือสนับสนุนส่วนขยาย Chrome นี้ เพลงฟรีบน Google Drive ™ไม่ได้เป็นเจ้าของไม่ได้รับอนุญาตจากและไม่ใช่ บริษัท ในเครือของ Google Inc.",
    "tr": "Müziğinizi Google Drive ™ ile ücretsiz olarak hızlıca çalın. Rahatsız edici reklamlar şarkılarınızı kesintiye uğratmadan ücretsiz müzik dinleyin.\n\nGoogle Drive ™ 'da Ücretsiz Müzik, Google Drive'ınızdan çevrimiçi müzik dinlemenizi sağlayan ücretsiz bir çevrimiçi yazılımdır. Müzik dosyaları Google Drive'ınızda saklanır\n\nMüzik dinleyebilmeniz için önce bilgisayarınıza müzik indirmenize gerek yoktur. Doğrudan Google Drive'ınızdan müzik aktarmak ve hemen müzik dinlemek için çevrimiçi müzik çaları kullanabilirsiniz. Çok basit, birçok formatı destekliyoruz (aac, mp3, m4a, wav, ogg, weba, wma). Kurulum gerektirmez, maliyeti yoktur.\n\nYazılımımız Google Drive'dan en sevdiğiniz şarkıları dinlemenize yardımcı olacağından, bilgisayarınıza müzik indirmekten zaman kazanın.\n\nGoogle Drive ™ 'da Ücretsiz Müzik Kullanma Adımları\n1) Google Drive ™ 'a Ücretsiz Müzik yükleyin\n2) En sevdiğiniz şarkıları Google Drive ™ 'a yükleyin (Tek seferlik Yükleme)\n3) Şarkılarınızı Google Drive ™ 'dan çalmaya başlayın. Çevrimiçi olsanız, nerede olursanız olun şarkılarınıza erişin\n\nBu, Spotify'dan daha iyidir çünkü kendi özel çalma listelerinizi oluşturabilirsiniz ve dinleme deneyimini bozacak hiçbir reklam yoktur. Tek sınır hayal gücünüzdür!\n\nSorumluluk Reddi Beyanı: Lütfen bu uzantının Google tarafından OLMADIĞINI ve bağımsız bir geliştirme ekibi tarafından yapıldığını unutmayın. Tüm telif hakları kendi sahiplerine aittir. Google, bu Chrome uzantısını onaylamaz veya desteklemez. Google Drive ™ üzerinde Ücretsiz Müzik, Google Inc.'e ait değildir, lisansı yoktur ve bir Google Inc. yan kuruluşu değildir.",
    "uk": "Швидко відтворюйте свою музику з Google Drive ™. Слухайте музику безкоштовно, без набридливих оголошень, що переривають ваші пісні.\n\nБезкоштовна музика на Google Drive ™ - це безкоштовне програмне забезпечення для Інтернету, яке дозволяє слухати музику в Інтернеті з вашого Google Drive. Музичні файли зберігаються на вашому Google Drive\n\nВам не потрібно завантажувати музику на комп’ютер, перш ніж слухати музику. За допомогою онлайн-музичного програвача можна імпортувати музику безпосередньо з вашого Google Drive і відразу слухати музику. Це просто, ми підтримуємо багато форматів (aac, mp3, m4a, wav, ogg, weba, wma). Установка не потрібна, витрати відсутні.\n\nЕкономте свій час від завантаження музики на комп’ютер, оскільки наше програмне забезпечення допоможе вам слухати ваші улюблені пісні з Google Drive.\n\nКроки для використання безкоштовної музики на Google Drive ™\n1) Встановіть безкоштовну музику на Google Drive ™\n2) Завантажте улюблені пісні на свій Google Drive ™ (одноразове завантаження)\n3) Почніть відтворювати свої пісні з Google Drive ™. Майте доступ до своїх пісень незалежно від того, де ви знаходитесь, якщо ви перебуваєте в Інтернеті\n\nЦе краще, ніж Spotify, тому що ви можете створювати власні власні списки відтворення, і немає реклами, яка порушить досвід прослуховування. Єдина межа - ваша фантазія!\n\nЗастереження. Зверніть увагу: це розширення НЕ робиться компанією Google, а робиться незалежною командою розробників. Усі авторські права належать їх власникам. Google не підтримує та не спонсорує це розширення Chrome. Безкоштовна музика на Google Drive ™ не належить, не ліцензована та не є дочірньою компанією Google Inc.",
    "vi": "Phát nhạc của bạn nhanh chóng miễn phí từ Google Drive ™. Nghe nhạc miễn phí mà không có bất kỳ quảng cáo khó chịu nào làm gián đoạn bài hát của bạn.\n\nNhạc miễn phí trên Google Drive ™ là phần mềm trực tuyến miễn phí cho phép bạn nghe nhạc trực tuyến từ Google Drive của mình. Các tệp nhạc được lưu trữ trên Google Drive của bạn\n\nBạn không cần phải tải nhạc về máy tính trước khi có thể nghe nhạc. Bạn có thể sử dụng trình phát nhạc trực tuyến để nhập nhạc trực tiếp từ Google Drive của mình và nghe nhạc ngay lập tức. Thật đơn giản, chúng tôi hỗ trợ nhiều định dạng (aac, mp3, m4a, wav, ogg, weba, wma). Không cần cài đặt, không có chi phí.\n\nTiết kiệm thời gian tải nhạc xuống máy tính của bạn vì phần mềm của chúng tôi sẽ giúp bạn nghe các bài hát yêu thích từ Google Drive.\n\nCác bước sử dụng nhạc miễn phí trên Google Drive ™\n1) Cài đặt Nhạc miễn phí trên Google Drive ™\n2) Tải các bài hát yêu thích của bạn lên Google Drive ™ (Tải lên một lần)\n3) Bắt đầu phát các bài hát của bạn từ Google Drive ™. Có quyền truy cập vào các bài hát của bạn bất kể bạn ở đâu nếu bạn đang trực tuyến\n\nĐiều này tốt hơn Spotify vì bạn có thể tạo danh sách phát tùy chỉnh của riêng mình và không có quảng cáo làm gián đoạn trải nghiệm nghe. Giới hạn duy nhất là trí tưởng tượng của bạn!\n\nTuyên bố từ chối trách nhiệm: Xin lưu ý rằng tiện ích mở rộng này KHÔNG phải do Google tạo ra và được tạo bởi một nhóm phát triển độc lập. Mọi bản quyền thuộc về chủ sử hữu của chúng. Google không xác nhận hoặc tài trợ cho tiện ích mở rộng này của Chrome. Nhạc Miễn phí trên Google Drive ™ không thuộc sở hữu, không được cấp phép bởi và không phải là công ty con của Google Inc.",
    "zh_CN": "通过Google Drive™免费快速播放音乐。免费收听音乐，而没有任何烦人的广告打断您的歌曲。\n\nGoogle Drive™上的免费音乐是一款免费的在线软件，可让您从Google Drive上在线收听音乐。音乐文件存储在您的Google云端硬盘中\n\n您可以先将音乐下载到计算机上，然后再听音乐。您可以使用在线音乐播放器直接从Google云端硬盘导入音乐，然后立即收听音乐。很简单，我们支持多种格式（aac，mp3，m4a，wav，ogg，weba，wma）。无需安装，无需任何费用。\n\n节省您将音乐下载到计算机上的时间，因为我们的软件将帮助您从Google云端硬盘中收听喜欢的歌曲。\n\n在Google Drive™上使用免费音乐的步骤\n1）在Google Drive™上安装免费音乐\n2）将您喜欢的歌曲上传到Google Drive™（一次上传）\n3）开始从Google Drive™播放歌曲。无论您身在何处，都可以访问自己的歌曲\n\n这比Spotify更好，因为您可以创建自己的自定义播放列表，并且没有任何广告可以干扰收听体验。你的想象力是唯一的限制！\n\n免责声明：请注意，此扩展程序不是由Google而是由独立的开发团队开发的。所有版权属于其各自所有者。 Google不认可或赞助此Chrome扩展程序。 Google Drive™上的免费音乐不属于Google Inc.，也不属于Google Inc.的子公司。",
    "zh_TW": "通過Google Drive™免費快速播放音樂。免費收聽音樂，而沒有任何煩人的廣告打斷您的歌曲。\n\nGoogle Drive™上的免費音樂是一款免費的在線軟件，可讓您從Google Drive上在線收聽音樂。音樂文件存儲在您的Google雲端硬盤中\n\n您可以先將音樂下載到計算機上，然後再聽音樂。您可以使用在線音樂播放器直接從Google雲端硬盤導入音樂，然後立即收聽音樂。很簡單，我們支持多種格式（aac，mp3，m4a，wav，ogg，weba，wma）。無需安裝，無需任何費用。\n\n節省您將音樂下載到計算機上的時間，因為我們的軟件將幫助您從Google雲端硬盤中收聽喜歡的歌曲。\n\n在Google Drive™上使用免費音樂的步驟\n1）在Google Drive™上安裝免費音樂\n2）將您喜歡的歌曲上傳到Google Drive™（一次上傳）\n3）開始從Google Drive™播放歌曲。無論您身在何處，都可以訪問自己的歌曲\n\n這比Spotify更好，因為您可以創建自己的自定義播放列表，並且沒有任何廣告可以乾擾收聽體驗。你的想像力是唯一的限制！\n\n免責聲明：請注意，此擴展程序不是由Google而是由獨立的開發團隊開發的。所有版權屬於其各自所有者。 Google不認可或贊助此Chrome擴展程序。 Google Drive™上的免費音樂不屬於Google Inc.，也不屬於Google Inc.的子公司。"
  }
}