{
  "name": {
    "ar": "المتوسع النص التلقائي المجاني",
    "am,bn,en,en_AU,en_GB,en_US,es_419,gu,kn,ml,mr,pt_BR,pt_PT,sw,ta,te": "Free Auto Text Expander",
    "bg": "Безплатен автоматичен разширител на текст",
    "ca": "Ampliador de text automàtic gratuït",
    "cs": "Zdarma Auto Text Expander",
    "da": "Gratis automatisk tekstudvidelse",
    "de": "Kostenloser Auto Text Expander",
    "el": "Δωρεάν αυτόματη επέκταση κειμένου",
    "es": "Expansor de texto automático gratuito",
    "et": "Tasuta automaatne tekstilaiendaja",
    "fa": "گسترش دهنده متن خودکار رایگان",
    "fi": "Ilmainen automaattinen tekstin laajennus",
    "fil": "Libreng Auto Text Expander",
    "fr": "Expanseur de texte automatique gratuit",
    "he": "מרחיב טקסט אוטומטי בחינם",
    "hi": "फ्री ऑटो टेक्स्ट एक्सपैंडर",
    "hr": "Besplatno automatsko širenje teksta",
    "hu": "Ingyenes automatikus szövegbővítő",
    "id": "Ekspander Teks Otomatis Gratis",
    "it": "Espansore di testo automatico gratuito",
    "ja": "無料の自動テキストエキスパンダー",
    "ko": "무료 자동 텍스트 확장기",
    "lt": "Nemokamas automatinis teksto plėtinys",
    "lv": "Bezmaksas automātiskais teksta paplašinātājs",
    "ms": "Pengembang Teks Auto Percuma",
    "nl": "Gratis automatische tekstuitbreiding",
    "no": "Gratis automatisk tekstutvidelse",
    "pl": "Darmowy automatyczny ekspander tekstu",
    "ro": "Expandator gratuit de text auto",
    "ru": "Бесплатный автоматический расширитель текста",
    "sk": "Bezplatný automatický textový expandér",
    "sl": "Brezplačni samodejni ekspander besedila",
    "sr": "Бесплатно аутоматско ширење текста",
    "sv": "Gratis Auto Text Expander",
    "th": "ขยายข้อความอัตโนมัติฟรี",
    "tr": "Ücretsiz Otomatik Metin Genişletici",
    "uk": "Безкоштовний автоматичний розширювач тексту",
    "vi": "Mở rộng văn bản tự động miễn phí",
    "zh_CN": "免费自动文本扩展器",
    "zh_TW": "免費自動文本擴展器"
  },
  "short": {
    "ar": "إنشاء اختصارات لوحة المفاتيح المخصصة لتوسيع واستبدال النص أثناء الكتابة!",
    "am,bn,en,en_AU,en_GB,en_US,es_419,gu,kn,ml,mr,pt_BR,pt_PT,sw,ta,te": "Create custom keyboard shortcuts to expand and replace text as you type!",
    "bg": "Създайте персонализирани клавишни комбинации за разширяване и замяна на текст, докато пишете!",
    "ca": "Creeu dreceres de teclat personalitzades per ampliar i substituir el text mentre escriviu.",
    "cs": "Vytvořte si vlastní klávesové zkratky pro rozbalení a nahrazení textu během psaní!",
    "da": "Opret tilpassede tastaturgenveje for at udvide og erstatte tekst, mens du skriver!",
    "de": "Erstellen Sie benutzerdefinierte Tastaturkürzel, um Text während der Eingabe zu erweitern und zu ersetzen!",
    "el": "Δημιουργήστε προσαρμοσμένες συντομεύσεις πληκτρολογίου για να αναπτύξετε και να αντικαταστήσετε κείμενο όσο πληκτρολογείτε!",
    "es": "¡Crea atajos de teclado personalizados para expandir y reemplazar texto mientras escribes!",
    "et": "Looge kohandatud kiirklahve teksti laiendamiseks ja asendamiseks tippimise ajal!",
    "fa": "برای گسترش و جایگزینی متن به عنوان تایپ ، میانبرهای صفحه کلید سفارشی ایجاد کنید!",
    "fi": "Luo mukautettuja pikanäppäimiä laajentaaksesi ja korvataksesi tekstiä kirjoittaessasi!",
    "fil": "Lumikha ng mga pasadyang mga shortcut sa keyboard upang mapalawak at palitan ang teksto habang nag-type ka!",
    "fr": "Créez des raccourcis clavier personnalisés pour développer et remplacer le texte à mesure que vous tapez!",
    "he": "צור קיצורי מקשים מותאמים אישית כדי להרחיב ולהחליף טקסט תוך כדי הקלדת!",
    "hi": "जैसे ही आप टाइप करें और टेक्स्ट को बदलने के लिए कस्टम कीबोर्ड शॉर्टकट बनाएं!",
    "hr": "Stvorite prilagođene prečace na tipkovnici za širenje i zamjenu teksta dok kucate!",
    "hu": "Készítsen egyedi billentyűparancsokat a szöveg kibővítéséhez és cseréjéhez gépelés közben!",
    "id": "Buat pintasan keyboard khusus untuk memperluas dan mengganti teks saat Anda mengetik!",
    "it": "Crea scorciatoie da tastiera personalizzate per espandere e sostituire il testo durante la digitazione!",
    "ja": "入力時にテキストを展開および置換するカスタムキーボードショートカットを作成します！",
    "ko": "입력 할 때 텍스트를 확장하고 바꾸는 사용자 정의 키보드 단축키를 만드십시오!",
    "lt": "Sukurkite pasirinktinius sparčiuosius klavišus, kad išplėstumėte ir pakeistumėte tekstą rašydami!",
    "lv": "Izveidojiet pielāgotos īsinājumtaustiņus, lai paplašinātu un aizstātu tekstu rakstīšanas laikā.",
    "ms": "Buat pintasan papan kekunci tersuai untuk mengembangkan dan menggantikan teks semasa anda menaip!",
    "nl": "Maak aangepaste sneltoetsen om tekst uit te breiden en te vervangen terwijl u typt!",
    "no": "Lag egendefinerte tastatursnarveier for å utvide og erstatte tekst mens du skriver!",
    "pl": "Twórz własne skróty klawiaturowe, aby rozszerzać i zamieniać tekst podczas pisania!",
    "ro": "Creați comenzi rapide de la tastatură pentru a extinde și înlocui textul pe măsură ce tastați!",
    "ru": "Создавайте собственные сочетания клавиш для расширения и замены текста по мере ввода!",
    "sk": "Vytvorte vlastné klávesové skratky na rozšírenie a nahradenie textu počas písania!",
    "sl": "Ustvarite bližnjice na tipkovnici, če želite med tipkanjem razširiti in zamenjati besedilo!",
    "sr": "Креирајте прилагођене пречице за тастатуру како бисте проширили и заменили текст док куцате!",
    "sv": "Skapa anpassade kortkommandon för att expandera och ersätta text när du skriver!",
    "th": "สร้างแป้นพิมพ์ลัดที่กำหนดเองเพื่อขยายและแทนที่ข้อความในขณะที่คุณพิมพ์!",
    "tr": "Yazarken metni genişletmek ve değiştirmek için özel klavye kısayolları oluşturun!",
    "uk": "Створіть спеціальні комбінації клавіш для розширення та заміни тексту під час введення тексту!",
    "vi": "Tạo các phím tắt tùy chỉnh để mở rộng và thay thế văn bản khi bạn nhập!",
    "zh_CN": "创建自定义键盘快捷键，以在键入时扩展和替换文本！",
    "zh_TW": "創建自定義鍵盤快捷鍵，以在鍵入時擴展和替換文本！"
  },
  "long": {
    "ar": "أنشئ اختصارات لوحة مفاتيح مخصصة لتوسيع واستبدال النص أثناء الكتابة.\n\nهل سئمت من كتابة عناوين البريد الإلكتروني الطويلة ، أو العبارات التي تستخدمها بشكل متكرر ، أو مجرد البحث عن حفظ ضغطات المفاتيح أثناء الكتابة؟ حسنا لا تخف! Auto Text Expander موجود هنا لحل هذه المشكلة - مثل TextExpander لنظام التشغيل Mac أو النص التلقائي لنظام التشغيل Windows ، ولكن تم تثبيته ومزامنته عبر متصفحات Chrome!\n\nيضيف هذا الامتداد المجاني جافا سكريبت أساسيًا إلى صفحاتك للتحقق مما إذا كانت مجموعتك الأخيرة من ضغطات المفاتيح المتتالية تتطابق مع أي عدد من الاختصارات المخصصة التي يمكنك تحديدها وتوسيعها واستبدالها أثناء الكتابة. وفر الوقت والأخطاء المطبعية والرضا عن كونك كسولًا جدًا",
    "am,bn,en,en_AU,en_GB,en_US,es_419,gu,kn,ml,mr,pt_BR,pt_PT,sw,ta,te": "Create custom keyboard shortcuts to expand and replace text as you type.\n\nEver get tired of typing out long email addresses, phrases you frequently use, or just looking to save keystrokes as you type? Well fear not! Auto Text Expander is here to solve that -- kinda like TextExpander for Mac or AutoText for Windows, but installed and synced across Chrome browsers!\n\nThis free extension adds basic javascript to your pages to check if your last set of consecutive keystrokes matches any of any number of custom shortcuts you can define and expands and replaces that text as you type. Save time, typos, and the satisfaction of being extra lazy!",
    "bg": "Създайте персонализирани клавишни комбинации, за да разширите и замените текста, докато пишете.\n\nВинаги ли ви е писнало да пишете дълги имейл адреси, фрази, които често използвате, или просто да търсите да запазите натискания на клавиши, докато пишете? Ами не се страхувайте! Auto Text Expander е тук, за да реши това - нещо като TextExpander за Mac или AutoText за Windows, но инсталиран и синхронизиран в браузърите Chrome!\n\nТова безплатно разширение добавя основен javascript към вашите страници, за да провери дали последният ви набор от последователни натискания на клавиши съответства на произволен брой персонализирани преки пътища, които можете да дефинирате, и разширява и замества този текст, докато пишете. Спестете време, печатни грешки и удовлетворението от това, че сте много мързеливи!",
    "ca": "Creeu dreceres de teclat personalitzades per ampliar i substituir el text mentre escriviu.\n\nUs heu cansat d’escriure adreces electròniques llargues, frases que utilitzeu sovint o simplement voleu desar les pulsacions de tecles mentre escriviu? Doncs no us temeu! Auto Text Expander és aquí per solucionar-ho, com TextExpander per a Mac o AutoText per a Windows, però instal·lat i sincronitzat als navegadors Chrome.\n\nAquesta extensió gratuïta afegeix javascript bàsic a les vostres pàgines per comprovar si l'últim conjunt de pulsacions de tecles consecutives coincideix amb qualsevol nombre de dreceres personalitzades que podeu definir, ampliar i substituir aquest text a mesura que escriviu. Estalvieu temps, errors tipogràfics i la satisfacció de ser més mandrós.",
    "cs": "Vytvářejte vlastní klávesové zkratky, pomocí kterých můžete text během psaní rozšiřovat a nahrazovat.\n\nUž vás někdy omrzelo vypisovat dlouhé e-mailové adresy, fráze, které často používáte, nebo se jen díváte na ukládání stisků kláves během psaní? Nebojte se! Auto Text Expander je tu, aby to vyřešil - trochu jako TextExpander pro Mac nebo AutoText pro Windows, ale nainstalovaný a synchronizovaný ve všech prohlížečích Chrome!\n\nToto bezplatné rozšíření přidává na vaše stránky základní javascript, který kontroluje, zda vaše poslední sada po sobě jdoucích stisků kláves odpovídá libovolnému počtu vlastních zkratek, které můžete definovat, a rozšiřuje a nahrazuje tento text při psaní. Ušetřete čas, překlepy a uspokojení z toho, že jste mimořádně líní!",
    "da": "Opret brugerdefinerede tastaturgenveje for at udvide og erstatte tekst, mens du skriver.\n\nBliver du nogensinde træt af at skrive lange e-mail-adresser, sætninger, du ofte bruger, eller bare ønsker at gemme tastetryk, mens du skriver? Nå frygt ikke! Auto Text Expander er her for at løse det - lidt som TextExpander til Mac eller AutoText til Windows, men installeret og synkroniseret på tværs af Chrome-browsere!\n\nDenne gratis udvidelse tilføjer grundlæggende javascript til dine sider for at kontrollere, om dit sidste sæt på hinanden følgende tastetryk matcher et hvilket som helst antal brugerdefinerede genveje, du kan definere og udvider og erstatter den tekst, mens du skriver. Spar tid, skrivefejl og tilfredsheden med at være ekstra doven!",
    "de": "Erstellen Sie benutzerdefinierte Tastaturkürzel, um Text während der Eingabe zu erweitern und zu ersetzen.\n\nHaben Sie es jemals satt, lange E-Mail-Adressen, häufig verwendete Phrasen oder nur das Speichern von Tastenanschlägen während der Eingabe einzugeben? Nun fürchte dich nicht! Auto Text Expander ist hier, um das zu lösen - ein bisschen wie TextExpander für Mac oder AutoText für Windows, aber installiert und synchronisiert über Chrome-Browser!\n\nDiese kostenlose Erweiterung fügt Ihren Seiten grundlegendes Javascript hinzu, um zu überprüfen, ob Ihre letzten aufeinanderfolgenden Tastenanschläge mit einer beliebigen Anzahl von benutzerdefinierten Verknüpfungen übereinstimmen, die Sie während der Eingabe definieren, erweitern und ersetzen können. Sparen Sie Zeit, Tippfehler und die Befriedigung, besonders faul zu sein!",
    "el": "Δημιουργήστε προσαρμοσμένες συντομεύσεις πληκτρολογίου για ανάπτυξη και αντικατάσταση κειμένου καθώς πληκτρολογείτε.\n\nΈχετε κουραστεί να πληκτρολογείτε μεγάλες διευθύνσεις email, φράσεις που χρησιμοποιείτε συχνά ή απλά θέλετε να αποθηκεύσετε πληκτρολογήσεις καθώς πληκτρολογείτε; Φοβάστε όχι! Το Auto Text Expander είναι εδώ για να το λύσει - όπως το TextExpander για Mac ή το AutoText για Windows, αλλά έχει εγκατασταθεί και συγχρονιστεί σε προγράμματα περιήγησης Chrome!\n\nΑυτή η δωρεάν επέκταση προσθέτει βασικό javascript στις σελίδες σας για να ελέγξει αν το τελευταίο σας σύνολο διαδοχικών πληκτρολογήσεων αντιστοιχεί σε οποιονδήποτε αριθμό προσαρμοσμένων συντομεύσεων που μπορείτε να ορίσετε και να επεκτείνετε και να αντικαταστήσετε αυτό το κείμενο καθώς πληκτρολογείτε. Εξοικονομήστε χρόνο, τυπογραφικά λάθη και την ικανοποίηση του να είστε πιο τεμπέλης",
    "es": "Cree atajos de teclado personalizados para expandir y reemplazar texto a medida que escribe.\n\n¿Alguna vez se cansó de escribir largas direcciones de correo electrónico, frases que usa con frecuencia o simplemente buscar guardar las pulsaciones de teclas mientras escribe? ¡No temas! Auto Text Expander está aquí para resolver eso, algo así como TextExpander para Mac o AutoText para Windows, ¡pero instalado y sincronizado en los navegadores Chrome!\n\nEsta extensión gratuita agrega javascript básico a sus páginas para verificar si su último conjunto de pulsaciones de teclas consecutivas coincide con cualquiera de los accesos directos personalizados que puede definir y expande y reemplaza ese texto a medida que escribe. ¡Ahorre tiempo, errores tipográficos y la satisfacción de ser más vago!",
    "et": "Teksti laiendamiseks ja asendamiseks looge kohandatud klaviatuuri otseteed.\n\nKas olete kunagi väsinud pikkade e-posti aadresside, sageli kasutatavate fraaside välja kirjutamisest või lihtsalt sisestamise ajal klahvivajutuste salvestamisest? No ära karda! Automaatne teksti laiendaja on siin selle lahendamiseks - nagu näiteks TextExpander Macile või AutoText Windowsile, kuid installitud ja sünkroonitud Chrome'i brauserites!\n\nSee tasuta laiendus lisab teie lehtedele põhilise javascripti, et kontrollida, kas teie viimane järjestikuste klahvivajutuste komplekt sobib mis tahes arvuga kohandatud otseteedega, mida saate teksti määramisel määratleda, laiendades ja asendades. Säästke aega, kirjavigu ja rahulolu sellega, et olete eriti laisk!",
    "fa": "برای گسترش و جایگزینی متن هنگام تایپ ، میانبرهای صفحه کلید سفارشی ایجاد کنید.\n\nآیا تا به حال از نوشتن آدرس های ایمیل طولانی ، عباراتی که مرتباً استفاده می کنید یا فقط به دنبال ذخیره کلیدهای حین تایپ خود خسته شده اید؟ خوب نترس! Auto Text Expander برای حل آن اینجا است - تقریباً مانند TextExpander برای Mac یا AutoText برای Windows ، اما در مرورگرهای Chrome نصب و همگام سازی شده است!\n\nاین افزونه رایگان جاوا اسکریپت اساسی را به صفحات شما اضافه می کند تا بررسی کند آیا آخرین مجموعه کلیدهای متوالی شما با هر تعداد میانبر سفارشی که می توانید تعریف کنید مطابقت دارد یا متن را هنگام تایپ گسترش و جایگزین می کند. در وقت ، اشتباه تایپی و رضایت از تنبلی اضافی صرفه جویی کنید!",
    "fi": "Luo mukautettuja pikanäppäimiä laajentaaksesi ja korvataksesi tekstiä kirjoittaessasi.\n\nOnko ikinä kyllästynyt kirjoittamaan pitkiä sähköpostiosoitteita, usein käyttämiäsi lauseita tai vain tallentamaan näppäinpainalluksia kirjoittaessasi? No, älä pelkää! Automaattinen tekstin laajennus on täällä ratkaistava - kinda kuten TextExpander Macille tai AutoText Windowsille, mutta asennettu ja synkronoitu Chromen selaimiin!\n\nTämä ilmainen laajennus lisää perustiedot JavaScriptiisi sivuillesi tarkistaaksesi, vastaako viimeinen peräkkäisten näppäinpainikkeiden joukko minkä tahansa määrän määrittelemiä mukautettuja pikakuvakkeita, laajentaa ja korvaa kyseisen tekstin kirjoittaessasi. Säästä aikaa, kirjoitusvirheitä ja tyytyväisyyttä olla erityisen laiska!",
    "fil": "Luo mukautettuja pikanäppäimiä laajentaaksesi ja korvaamaan tekstiä kirjoittaessasi.\n\nOletko koskaan kyllästynyt kirjoittamaan pitkiä sähköpostiosoitteita, usein käyttämiäsi lauseita tai etsimään vain näppäilyjen tallentamista kirjoittaessasi? Älä pelkää! Automaattinen tekstilaajennin on täällä ratkaisemaan sen - tavallaan kuten TextExpander for Mac tai AutoText for Windows, mutta asennettu ja synkronoitu Chrome-selaimissa!\n\nTämä ilmainen laajennus lisää sivujesi Javascriptin tarkistaaksesi, vastaavatko viimeiset peräkkäiset näppäinpainallukset mitä tahansa määrittämäsi mukautettua pikanäppäintä, jonka voit määrittää ja laajentaa ja korvaa kyseisen tekstin kirjoittaessasi. Säästä aikaa, kirjoitusvirheitä ja tyydytystä ylimääräisestä laiskuudesta!",
    "fr": "Créez des raccourcis clavier personnalisés pour développer et remplacer le texte à mesure que vous tapez.\n\nVous êtes-vous déjà fatigué de taper de longues adresses e-mail, des phrases que vous utilisez fréquemment ou simplement de vouloir enregistrer des frappes au fur et à mesure que vous tapez? Eh bien, n'ayez pas peur! Auto Text Expander est là pour résoudre ce problème - un peu comme TextExpander pour Mac ou AutoText pour Windows, mais installé et synchronisé sur les navigateurs Chrome!\n\nCette extension gratuite ajoute du javascript de base à vos pages pour vérifier si votre dernier ensemble de frappes consécutives correspond à l'un des nombreux raccourcis personnalisés que vous pouvez définir, étend et remplace ce texte au fur et à mesure que vous tapez. Gagnez du temps, des fautes de frappe et la satisfaction d'être très paresseux!",
    "he": "צור קיצורי מקשים מותאמים אישית כדי להרחיב ולהחליף טקסט בזמן ההקלדה.\n\nהאם אי פעם נמאס לך להקליד כתובות דוא\"ל ארוכות, ביטויים שאתה מרבה להשתמש בהם או פשוט מחפש לשמור הקשות בזמן שאתה מקליד? ובכן, אל תפחדו! Auto Text Expander נמצא כאן כדי לפתור זאת - די כמו TextExpander עבור Mac או AutoText עבור Windows, אך מותקן ומסונכרן בין דפדפני Chrome!\n\nתוסף חופשי זה מוסיף ג'אווה סקריפט בסיסי לדפים שלך בכדי לבדוק אם קבוצת ההקשות האחרונות שלך ברציפות תואמת לכל אחד ממספר קיצורי הדרך המותאמים אישית שתוכל להגדיר ולהרחיב ומחליף טקסט זה תוך כדי הקלדה. חסוך זמן, שגיאות הקלדה והסיפוק מלהיות עצלן במיוחד!",
    "hi": "जैसे ही आप टाइप करें और टेक्स्ट को बदलने के लिए कस्टम कीबोर्ड शॉर्टकट बनाएं।\n\nकभी लंबे ईमेल पतों को टाइप करते हुए थक जाते हैं, जिन वाक्यांशों का आप अक्सर उपयोग करते हैं, या जैसे ही आप लिखते हैं किस्ट्रोक्स को बचाने के लिए देख रहे हैं? खैर डर नहीं! ऑटो टेक्स्ट एक्सपैंडर को हल करने के लिए यहाँ है - जैसे कि Mac के लिए TextExpander या Windows के लिए AutoText, लेकिन क्रोम ब्राउज़र में स्थापित और सिंक किया गया!\n\nयह मुफ्त एक्सटेंशन आपके पृष्ठों में बुनियादी जावास्क्रिप्ट जोड़ता है यह जांचने के लिए कि क्या आपके लगातार कीस्ट्रोक्स का अंतिम सेट किसी भी कस्टम शॉर्टकट की किसी भी संख्या से मेल खाता है और आप उस पाठ को टाइप और बदलने और बदलने में बदल सकते हैं। अतिरिक्त आलसी होने का समय, टाइपो, और संतुष्टि बचाओ!",
    "hr": "Stvorite prilagođene tipkovne prečace za proširivanje i zamjenu teksta dok tipkate.\n\nJe li vam se ikad dosadilo upisivati dugačke adrese e-pošte, fraze koje često koristite ili jednostavno spremati pritiske tipki dok tipkate? Pa ne bojte se! Auto Text Expander je ovdje da to riješi - nekako poput TextExpander za Mac ili AutoText za Windows, ali instaliran i sinkroniziran u Chrome preglednicima!\n\nOvo besplatno proširenje dodaje osnovni javascript na vaše stranice kako bi provjerilo podudara li se vaš posljednji niz uzastopnih tipki s bilo kojim brojem prilagođenih prečaca koje možete definirati te proširuje i zamjenjuje taj tekst dok upisujete. Uštedite vrijeme, pogreške pri upisu i zadovoljstvo zbog dodatne lijenosti!",
    "hu": "Hozzon létre egyéni billentyűparancsokat a szöveg kibontásához és helyettesítéséhez gépelés közben.\n\nBelefáradt már abba, hogy hosszú e-mail címeket, gyakran használt kifejezéseket írjon ki, vagy csak arra törekedjen, hogy gépelés közben mentse a billentyűleütéseket? Hát ne félj! Az Auto Text Expander itt van, hogy megoldja ezt - olyan, mint a TextExpander for Mac vagy az AutoText for Windows, de telepítve és szinkronizálva a Chrome böngészőkben!\n\nEz az ingyenes kiterjesztés alapvető javascriptet ad hozzá az oldalaihoz, hogy ellenőrizze, hogy az utolsó egymást követő billentyűleütések megegyeznek-e a tetszőleges számú egyéni parancsikon bármelyikével, amelyet beírhat, és kibővítheti, illetve helyettesítheti a szöveget gépelés közben. Takarítson meg időt, elírási hibákat és az elégedettségét, hogy extra lusta!",
    "id": "Buat pintasan keyboard khusus untuk memperluas dan mengganti teks saat Anda mengetik.\n\nPernah bosan mengetik alamat email yang panjang, frasa yang sering Anda gunakan, atau hanya ingin menyimpan penekanan tombol saat Anda mengetik? Jangan takut! Auto Text Expander hadir untuk menyelesaikannya - seperti TextExpander untuk Mac atau AutoText untuk Windows, tetapi diinstal dan disinkronkan di browser Chrome!\n\nEkstensi gratis ini menambahkan javascript dasar ke halaman Anda untuk memeriksa apakah rangkaian penekanan tombol berturut-turut terakhir Anda cocok dengan salah satu dari sejumlah pintasan khusus yang dapat Anda tentukan dan memperluas serta mengganti teks tersebut saat Anda mengetik. Hemat waktu, kesalahan ketik, dan kepuasan menjadi ekstra malas!",
    "it": "Crea scorciatoie da tastiera personalizzate per espandere e sostituire il testo durante la digitazione.\n\nTi sei mai stancato di digitare lunghi indirizzi e-mail, frasi che usi frequentemente o semplicemente di salvare le sequenze di tasti durante la digitazione? Beh, non temere! Auto Text Expander è qui per risolverlo, un po 'come TextExpander per Mac o Testo automatico per Windows, ma installato e sincronizzato su tutti i browser Chrome!\n\nQuesta estensione gratuita aggiunge javascript di base alle tue pagine per verificare se l'ultima serie di sequenze di tasti consecutive corrisponde a un numero qualsiasi di scorciatoie personalizzate che puoi definire ed espande e sostituisce quel testo durante la digitazione. Risparmia tempo, errori di battitura e la soddisfazione di essere più pigro!",
    "ja": "入力時にテキストを展開および置換するカスタムキーボードショートカットを作成します。\n\n長いメールアドレスや頻繁に使用するフレーズを入力したり、入力時にキーストロークを保存したりすることに飽き飽きしたことはありませんか。恐れることはありません！ Auto Text Expanderは、それを解決するためにここにあります-Mac用のTextExpanderやWindows用のAutoTextのようなものですが、Chromeブラウザ間でインストールおよび同期されます！\n\nこの無料の拡張機能は、基本的なJavaScriptをページに追加して、連続するキーストロークの最後のセットが、定義可能な任意の数のカスタムショートカットのいずれかに一致するかどうかを確認し、入力時にそのテキストを展開して置き換えます。時間、タイプミス、そして余分な怠惰であることの満足感を節約してください！",
    "ko": "사용자 지정 키보드 단축키를 만들어 입력 할 때 텍스트를 확장하고 바꿉니다.\n\n긴 이메일 주소, 자주 사용하는 구문을 입력하거나 입력 할 때 키 입력을 저장하는 데 지쳐 본 적이 있습니까? 걱정하지 마세요! Auto Text Expander는 Mac 용 TextExpander 또는 Windows 용 AutoText와 비슷하지만 Chrome 브라우저간에 설치 및 동기화되었습니다.\n\n이 무료 확장 프로그램은 페이지에 기본 자바 스크립트를 추가하여 마지막 연속 키 입력 세트가 정의 할 수있는 사용자 지정 바로 가기와 일치하는지 확인하고 입력 할 때 해당 텍스트를 확장 및 대체합니다. 시간, 오타 및 게으른 만족도를 절약하십시오!",
    "lt": "Sukurkite pasirinktinius sparčiuosius klavišus, kad išplėstumėte ir pakeistumėte tekstą rašydami.\n\nAr kada atsibodo vesti ilgus el. Pašto adresus, frazes, kurias dažnai naudojate, ar tiesiog norite įrašyti klaviatūros klavišus? Na nebijok! „Auto Text Expander“ yra čia, kad išspręstumėte tai - panašiai kaip „TextExpander“, skirtą „Mac“, arba „AutoText“, skirtą „Windows“, tačiau įdiegtas ir sinchronizuotas „Chrome“ naršyklėse!\n\nŠis nemokamas plėtinys prideda pagrindinį „javascript“ prie jūsų puslapių, kad patikrintų, ar paskutiniai nuoseklūs klavišų paspaudimų rinkiniai atitinka bet kurį iš pasirinktinių sparčiųjų klavišų, kuriuos galite apibrėžti, išplėsti ir pakeisti, kai įvedate tekstą. Sutaupykite laiko, rašybos klaidų ir pasitenkinimo tuo, kad esate ypač tingus!",
    "lv": "Izveidojiet pielāgotus īsinājumtaustiņus, lai izvērstu un aizstātu tekstu rakstīšanas laikā.\n\nVai jums kādreiz ir apnicis rakstīt garas e-pasta adreses, frāzes, kuras bieži lietojat, vai vienkārši vēlaties saglabāt taustiņsitienus rakstīšanas laikā? Nu nebaidies! Automātiskais teksta paplašinātājs ir šeit, lai to atrisinātu - kaut kas līdzīgs TextExpander Mac vai AutoText operētājsistēmai Windows, taču ir instalēts un sinhronizēts Chrome pārlūkprogrammās!\n\nŠis bezmaksas paplašinājums jūsu lapām pievieno pamata javascript, lai pārbaudītu, vai pēdējais secīgo taustiņu taustiņu kopums atbilst jebkuram no pielāgoto īsinājumtaustiņu skaita, kurus varat definēt, kā arī izvēršot un aizstājot šo tekstu, rakstot. Ietaupiet laiku, kļūdas un gandarījumu par to, ka esat ļoti slinks!",
    "ms": "Buat pintasan papan kekunci tersuai untuk mengembangkan dan mengganti teks semasa anda menaip.\n\nPernah bosan menaip alamat e-mel yang panjang, frasa yang sering anda gunakan, atau hanya ingin menyimpan ketukan kekunci semasa anda menaip? Jangan takut! Auto Text Expander ada di sini untuk menyelesaikannya - seperti TextExpander untuk Mac atau AutoText untuk Windows, tetapi dipasang dan diselaraskan di seluruh penyemak imbas Chrome!\n\nSambungan percuma ini menambah javascript asas ke halaman anda untuk memeriksa sama ada set penekanan kekunci terakhir berturut-turut sesuai dengan sebilangan besar pintasan tersuai yang dapat anda tentukan dan kembangkan dan ganti teks itu semasa anda menaip. Jimat masa, kesalahan ketik, dan kepuasan kerana terlalu malas!",
    "nl": "Maak aangepaste sneltoetsen om tekst uit te vouwen en te vervangen terwijl u typt.\n\nBent u het ooit beu geworden om lange e-mailadressen, woordgroepen die u vaak gebruikt of gewoon toetsaanslagen op te slaan terwijl u typt? Nou, vrees niet! Auto Text Expander is hier om dat op te lossen - een beetje zoals TextExpander voor Mac of AutoText voor Windows, maar geïnstalleerd en gesynchroniseerd met Chrome-browsers!\n\nDeze gratis extensie voegt standaard javascript toe aan uw pagina's om te controleren of uw laatste reeks opeenvolgende toetsaanslagen overeenkomt met een willekeurig aantal aangepaste snelkoppelingen die u kunt definiëren en vergroot en vervangt die tekst terwijl u typt. Bespaar tijd, typefouten en de voldoening om extra lui te zijn!",
    "no": "Lag egendefinerte hurtigtaster for å utvide og erstatte tekst mens du skriver.\n\nHar du noen gang blitt lei av å skrive ut lange e-postadresser, setninger du ofte bruker, eller bare ønsker å lagre tastetrykk mens du skriver? Vel frykt ikke! Auto Text Expander er her for å løse det - som TextExpander for Mac eller AutoText for Windows, men installert og synkronisert på tvers av Chrome-nettlesere!\n\nDenne gratis utvidelsen legger til grunnleggende javascript på sidene dine for å sjekke om ditt siste sett med påfølgende tastetrykk samsvarer med et hvilket som helst antall egendefinerte snarveier du kan definere, utvider og erstatter teksten mens du skriver. Spar tid, skrivefeil og tilfredsheten med å være ekstra lat!",
    "pl": "Twórz niestandardowe skróty klawiaturowe, aby rozszerzać i zamieniać tekst podczas pisania.\n\nMasz dość wpisywania długich adresów e-mail, często używanych fraz lub po prostu chęci zapisywania naciśnięć klawiszy podczas pisania? Nie bój się! Auto Text Expander jest tutaj, aby rozwiązać ten problem - trochę jak TextExpander na Maca lub Autotekst dla Windows, ale jest zainstalowany i zsynchronizowany w przeglądarkach Chrome!\n\nTo bezpłatne rozszerzenie dodaje podstawowy skrypt javascript do twoich stron, aby sprawdzić, czy twój ostatni zestaw kolejnych naciśnięć klawiszy pasuje do dowolnej liczby niestandardowych skrótów, które możesz zdefiniować, i rozwija i zastępuje ten tekst podczas pisania. Oszczędzaj czas, literówki i satysfakcję z bycia wyjątkowo leniwym!",
    "ro": "Creați comenzi rapide de la tastatură personalizate pentru a extinde și a înlocui textul pe măsură ce introduceți text.\n\nV-ați săturat vreodată să tastați adrese de e-mail lungi, fraze pe care le folosiți frecvent sau căutați doar să salvați apăsările de taste în timp ce tastați? Ei bine, nu vă temeți! Auto Text Expander este aici pentru a rezolva asta - cum ar fi TextExpander pentru Mac sau AutoText pentru Windows, dar instalat și sincronizat în browserele Chrome!\n\nAceastă extensie gratuită adaugă javascript de bază paginilor dvs. pentru a verifica dacă ultimul set de apăsări de taste consecutive se potrivește cu orice număr de comenzi rapide personalizate pe care le puteți defini, extinde și înlocui textul pe măsură ce tastați. Economisiți timp, greșeli de scriere și satisfacția de a fi leneși!",
    "ru": "Создавайте собственные сочетания клавиш для расширения и замены текста при вводе.\n\nВы когда-нибудь устали набирать длинные адреса электронной почты, часто используемые фразы или просто хотите сохранить нажатие клавиш при вводе? Не бойся! Auto Text Expander здесь, чтобы решить эту проблему - вроде как TextExpander для Mac или AutoText для Windows, но устанавливается и синхронизируется между браузерами Chrome!\n\nЭто бесплатное расширение добавляет базовый javascript на ваши страницы, чтобы проверить, соответствует ли последний набор последовательных нажатий клавиш любому из любого количества настраиваемых сочетаний клавиш, которые вы можете определить, и расширяет и заменяет этот текст по мере ввода. Экономьте время, опечатки и удовольствие от ленивости!",
    "sk": "Vytvorte si vlastné klávesové skratky, pomocou ktorých budete pri písaní text zväčšovať a nahrádzať.\n\nUž vás niekedy omrzelo písanie dlhých e-mailových adries, fráz, ktoré často používate, alebo si len chcete ukladať stlačenia klávesov počas písania? No nebojte sa! Auto Text Expander je tu na to, aby to vyriešil - trochu ako TextExpander pre Mac alebo AutoText pre Windows, ale nainštalovaný a synchronizovaný vo všetkých prehliadačoch Chrome!\n\nToto bezplatné rozšírenie pridáva na vaše stránky základný javascript, aby bolo možné skontrolovať, či sa vaša posledná sada po sebe nasledujúcich stlačení kláves zhoduje s ľubovoľným počtom vlastných skratiek, ktoré môžete definovať, a ktoré tento text pri zadávaní rozšíria a nahradia. Ušetrite čas, preklepy a spokojnosť s tým, že ste mimoriadne leniví!",
    "sl": "Ustvarite bližnjice na tipkovnici po meri za razširitev in zamenjavo besedila med tipkanjem.\n\nSte se kdaj naveličali vnašati dolge e-poštne naslove, fraze, ki jih pogosto uporabljate, ali pa preprosto shraniti pritiske tipk med tipkanjem? Pa se ne boj! Auto Text Expander je tu, da to reši - nekako tako kot TextExpander za Mac ali AutoText za Windows, vendar nameščen in sinhroniziran v brskalnikih Chrome!\n\nTa brezplačna razširitev na vaše strani doda osnovni javascript, da preveri, ali se vaš zadnji zaporedni pritisk na tipko ujema s katerim koli številom bližnjic po meri, ki jih lahko določite, in besedilo med tipkanjem razširi in nadomesti. Prihranite čas, tipkarske napake in zadovoljstvo, da ste še posebej leni!",
    "sr": "Створите прилагођене тастерске пречице за проширивање и замену текста док куцате.\n\nДа ли вам се икад досадило да откуцате дугачке адресе е-поште, фразе које често користите или само желите да сачувате притиске тастера док куцате? Па не бојте се! Ауто Тект Екпандер је овде да то реши - некако као ТектЕкпандер за Мац или АутоТект за Виндовс, али инсталиран и синхронизован у Цхроме прегледачима!\n\nОво бесплатно проширење додаје основни јавасцрипт на ваше странице како би се проверило да ли се последњи низ узастопних тастера подудара са било којим бројем прилагођених пречица које можете дефинисати и проширује и замењује тај текст док куцате. Уштедите време, грешке у куцању и задовољство због додатног лења!",
    "sv": "Skapa anpassade kortkommandon för att expandera och ersätta text när du skriver.\n\nHar du någonsin tröttnat på att skriva ut långa e-postadresser, fraser som du ofta använder, eller bara vill spara tangenttryckningar när du skriver? Tja, var inte rädd! Auto Text Expander är här för att lösa det - ungefär som TextExpander för Mac eller AutoText för Windows, men installerat och synkroniserat över Chrome-webbläsare!\n\nDetta gratis tillägg lägger till grundläggande javaskript på dina sidor för att kontrollera om din senaste uppsättning på varandra följande tangenttryckningar matchar något av ett antal anpassade genvägar som du kan definiera och expanderar och ersätter den texten när du skriver. Spara tid, skrivfel och tillfredsställelsen att vara extra lat!",
    "th": "สร้างแป้นพิมพ์ลัดแบบกำหนดเองเพื่อขยายและแทนที่ข้อความขณะที่คุณพิมพ์\n\nเคยเบื่อกับการพิมพ์ที่อยู่อีเมลยาว ๆ วลีที่คุณใช้บ่อยหรือเพียงแค่ต้องการบันทึกการกดแป้นพิมพ์เมื่อคุณพิมพ์ อย่ากลัวเลย! Auto Text Expander อยู่ที่นี่เพื่อแก้ปัญหาเช่น TextExpander สำหรับ Mac หรือ AutoText สำหรับ Windows แต่ติดตั้งและซิงค์กับเบราว์เซอร์ Chrome!\n\nส่วนขยายฟรีนี้เพิ่มจาวาสคริปต์พื้นฐานให้กับหน้าเว็บของคุณเพื่อตรวจสอบว่าการกดแป้นพิมพ์ต่อเนื่องชุดสุดท้ายของคุณตรงกับทางลัดที่กำหนดเองจำนวนเท่าใดก็ได้ที่คุณสามารถกำหนดและขยายและแทนที่ข้อความนั้นขณะที่คุณพิมพ์ ประหยัดเวลาพิมพ์ผิดและพอใจกับการขี้เกียจเป็นพิเศษ!",
    "tr": "Yazarken metni genişletmek ve değiştirmek için özel klavye kısayolları oluşturun.\n\nUzun e-posta adreslerini, sık kullandığınız ifadeleri yazmaktan veya yalnızca yazarken tuş vuruşlarını kaydetmek istemekten bıktınız mı? Korkmayın! Otomatik Metin Genişletici bunu çözmek için burada - Mac için TextExpander veya Windows için Otomatik Metin gibi, ancak Chrome tarayıcıları arasında yüklü ve senkronize edilmiş!\n\nBu ücretsiz uzantı, son ardışık tuş vuruşlarınızın tanımlayabileceğiniz herhangi bir sayıda özel kısayolla eşleşip eşleşmediğini kontrol etmek için sayfalarınıza temel javascript ekler ve siz yazarken bu metni genişletir ve değiştirir. Zamandan, yazım hatalarından ve ekstra tembel olmanın memnuniyetinden tasarruf edin!",
    "uk": "Створюйте власні комбінації клавіш для розширення та заміни тексту під час набору тексту.\n\nВам ніколи не набридає друкувати довгі адреси електронної пошти, фрази, які ви часто використовуєте, або просто хочете зберегти натискання клавіш під час введення? Ну не бійтеся! Для розв’язання цього питання потрібен Auto Text Expander - як-от TextExpander для Mac або AutoText для Windows, але встановлений та синхронізований у браузерах Chrome!\n\nЦе безкоштовне розширення додає базовий javascript на ваші сторінки, щоб перевірити, чи відповідає останній набір послідовних натискань клавіш будь-якій кількості спеціальних ярликів, які ви можете визначити, а також розширює та замінює цей текст під час набору тексту. Економте час, друкарські помилки та задоволення від того, що ви дуже ліниві!",
    "vi": "Tạo phím tắt tùy chỉnh để mở rộng và thay thế văn bản khi bạn nhập.\n\nBạn đã bao giờ cảm thấy mệt mỏi với việc gõ các địa chỉ email dài, các cụm từ bạn thường sử dụng hoặc chỉ tìm cách lưu các lần gõ phím khi bạn nhập? Cũng đừng sợ! Auto Text Expander ở đây để giải quyết vấn đề đó - giống như TextExpander cho Mac hoặc AutoText cho Windows, nhưng được cài đặt và đồng bộ hóa trên các trình duyệt Chrome!\n\nTiện ích mở rộng miễn phí này thêm javascript cơ bản vào các trang của bạn để kiểm tra xem tập hợp các lần nhấn phím liên tiếp gần đây nhất của bạn có khớp với bất kỳ phím tắt tùy chỉnh nào mà bạn có thể xác định, mở rộng và thay thế văn bản đó khi bạn nhập hay không. Tiết kiệm thời gian, lỗi chính tả và sự hài lòng của việc lười biếng!",
    "zh_CN": "创建自定义键盘快捷键以在键入时展开和替换文本。\n\n是否曾经厌倦了键入长电子邮件地址，您经常使用的短语，或者只是想在键入时保存击键？好吧，不要害怕！ Auto Text Expander可以解决此问题-有点像Mac上的TextExpander或Windows上的AutoText，但可以在Chrome浏览器中安装并同步！\n\n这个免费的扩展程序将基本的javascript添加到您的页面，以检查您的最后一组连续击键是否与您可以定义的任意数量的自定义快捷键中的任何一个相匹配，并在您键入内容时对其进行扩展和替换。节省时间，错别字和额外懒惰的满足感！",
    "zh_TW": "創建自定義鍵盤快捷鍵以在鍵入時展開和替換文本。\n\n是否曾經厭倦了鍵入長電子郵件地址，您經常使用的短語，或者只是想在鍵入時保存擊鍵？好吧，不要害怕！ Auto Text Expander可以解決此問題-有點像Mac上的TextExpander或Windows上的AutoText，但可以在Chrome瀏覽器中安裝並同步！\n\n這個免費的擴展程序將基本的javascript添加到您的頁面，以檢查您的最後一組連續擊鍵是否與您可以定義的任意數量的自定義快捷鍵中的任何一個相匹配，並在您鍵入時擴展並替換該文本。節省時間，錯別字和額外懶惰的滿足感！"
  }
}